{"origin":"CN_NNS","salesman":"(미지정)","yyyymm":"202606","totals":{"bkg_count":130,"shipper_count":2,"fst_teu":318.0,"lst_teu":63.0,"cm1":23149.0,"w3_fst":0.0,"w3_lst":0.0,"w3_hi_fst":0.0,"lst_rate_w3":null,"hi_share_w3":null},"shippers":[{"shipper_no":"","shipper_name":"","grade":"","bkg_count":125,"fst_teu":308.0,"lst_teu":53.0,"cm1":23149.0,"w3_fst":0.0,"w3_lst":0.0,"hi_w3_fst":0.0,"cancel_teu":10.0,"lst_rate_w3":null,"hi_share_w3":null},{"shipper_no":"SUGZ06","shipper_name":"SHENZHEN UNIEVER LOGISTICS CO.,LTD","grade":"","bkg_count":5,"fst_teu":10.0,"lst_teu":10.0,"cm1":0.0,"w3_fst":0.0,"w3_lst":0.0,"hi_w3_fst":0.0,"cancel_teu":0.0,"lst_rate_w3":null,"hi_share_w3":null}],"bookings":[{"bkg_no":"CN06780799","shipper_no":"","shipper_name":"","pol":"","pod_country":"","pod":"","dly_country":"ID","dly_plc":"JKT","vsl":"","voy":"","lst_vsl":"JNGS","lst_voy":"0052S","lst_route":"KCS2","booking_date":"2026년 7월 1일","booking_schedule":"2026년 7월 1일","cancel_date":"","week_start_date":"2026년 06월 28일","lead_time_bkg_sche":"Week of Sailing (WOS)","yyyymm_bkg_sche":"202606","lst_status":"Waiting","fst_teu":1.0,"lst_teu":1.0,"norm_lst_teu":0.0,"cm1":511.0,"norm_cm1":0.0,"cm1_per_teu":511.0,"grade":"","route_profit":"고수익","shipper_profit_tag":"","is_w3":false,"is_hi":true,"is_route_hi":true,"is_normal":false,"is_lifted":false,"is_cancel":false},{"bkg_no":"CN06780804","shipper_no":"","shipper_name":"","pol":"","pod_country":"","pod":"","dly_country":"ID","dly_plc":"JKT","vsl":"","voy":"","lst_vsl":"JNGS","lst_voy":"0052S","lst_route":"KCS2","booking_date":"2026년 7월 1일","booking_schedule":"2026년 7월 1일","cancel_date":"","week_start_date":"2026년 06월 28일","lead_time_bkg_sche":"Week of Sailing (WOS)","yyyymm_bkg_sche":"202606","lst_status":"Waiting","fst_teu":1.0,"lst_teu":1.0,"norm_lst_teu":0.0,"cm1":511.0,"norm_cm1":0.0,"cm1_per_teu":511.0,"grade":"","route_profit":"고수익","shipper_profit_tag":"","is_w3":false,"is_hi":true,"is_route_hi":true,"is_normal":false,"is_lifted":false,"is_cancel":false},{"bkg_no":"CN06780828","shipper_no":"","shipper_name":"","pol":"","pod_country":"","pod":"","dly_country":"ID","dly_plc":"SRG","vsl":"","voy":"","lst_vsl":"JNGS","lst_voy":"0052S","lst_route":"KCS2","booking_date":"2026년 7월 1일","booking_schedule":"2026년 7월 1일","cancel_date":"","week_start_date":"2026년 06월 28일","lead_time_bkg_sche":"Week of Sailing (WOS)","yyyymm_bkg_sche":"202606","lst_status":"Waiting","fst_teu":2.0,"lst_teu":2.0,"norm_lst_teu":0.0,"cm1":1058.0,"norm_cm1":0.0,"cm1_per_teu":529.0,"grade":"","route_profit":"고수익","shipper_profit_tag":"","is_w3":false,"is_hi":true,"is_route_hi":true,"is_normal":false,"is_lifted":false,"is_cancel":false},{"bkg_no":"CN06780833","shipper_no":"","shipper_name":"","pol":"","pod_country":"","pod":"","dly_country":"ID","dly_plc":"SRG","vsl":"","voy":"","lst_vsl":"JNGS","lst_voy":"0052S","lst_route":"KCS2","booking_date":"2026년 7월 1일","booking_schedule":"2026년 7월 1일","cancel_date":"","week_start_date":"2026년 06월 28일","lead_time_bkg_sche":"Week of Sailing (WOS)","yyyymm_bkg_sche":"202606","lst_status":"Waiting","fst_teu":2.0,"lst_teu":2.0,"norm_lst_teu":0.0,"cm1":1058.0,"norm_cm1":0.0,"cm1_per_teu":529.0,"grade":"","route_profit":"고수익","shipper_profit_tag":"","is_w3":false,"is_hi":true,"is_route_hi":true,"is_normal":false,"is_lifted":false,"is_cancel":false},{"bkg_no":"CN06790443","shipper_no":"","shipper_name":"","pol":"","pod_country":"","pod":"","dly_country":"AE","dly_plc":"KLF","vsl":"","voy":"","lst_vsl":"JESN","lst_voy":"026B8W","lst_route":"AIMT","booking_date":"2026년 6월 27일","booking_schedule":"2026년 6월 27일","cancel_date":"","week_start_date":"2026년 06월 21일","lead_time_bkg_sche":"Week of Sailing (WOS)","yyyymm_bkg_sche":"202606","lst_status":"Waiting","fst_teu":2.0,"lst_teu":2.0,"norm_lst_teu":0.0,"cm1":0.0,"norm_cm1":0.0,"cm1_per_teu":0.0,"grade":"","route_profit":"","shipper_profit_tag":"","is_w3":false,"is_hi":false,"is_route_hi":false,"is_normal":false,"is_lifted":false,"is_cancel":false},{"bkg_no":"CN06790455","shipper_no":"","shipper_name":"","pol":"","pod_country":"","pod":"","dly_country":"AE","dly_plc":"KLF","vsl":"","voy":"","lst_vsl":"JESN","lst_voy":"026B8W","lst_route":"AIMT","booking_date":"2026년 6월 27일","booking_schedule":"2026년 6월 27일","cancel_date":"","week_start_date":"2026년 06월 21일","lead_time_bkg_sche":"Week of Sailing (WOS)","yyyymm_bkg_sche":"202606","lst_status":"Waiting","fst_teu":2.0,"lst_teu":2.0,"norm_lst_teu":0.0,"cm1":0.0,"norm_cm1":0.0,"cm1_per_teu":0.0,"grade":"","route_profit":"","shipper_profit_tag":"","is_w3":false,"is_hi":false,"is_route_hi":false,"is_normal":false,"is_lifted":false,"is_cancel":false},{"bkg_no":"CN06790459","shipper_no":"","shipper_name":"","pol":"","pod_country":"","pod":"","dly_country":"AE","dly_plc":"KLF","vsl":"","voy":"","lst_vsl":"JESN","lst_voy":"026B8W","lst_route":"AIMT","booking_date":"2026년 6월 27일","booking_schedule":"2026년 6월 27일","cancel_date":"","week_start_date":"2026년 06월 21일","lead_time_bkg_sche":"Week of Sailing (WOS)","yyyymm_bkg_sche":"202606","lst_status":"Waiting","fst_teu":2.0,"lst_teu":2.0,"norm_lst_teu":0.0,"cm1":0.0,"norm_cm1":0.0,"cm1_per_teu":0.0,"grade":"","route_profit":"","shipper_profit_tag":"","is_w3":false,"is_hi":false,"is_route_hi":false,"is_normal":false,"is_lifted":false,"is_cancel":false},{"bkg_no":"CN06790463","shipper_no":"","shipper_name":"","pol":"","pod_country":"","pod":"","dly_country":"AE","dly_plc":"KLF","vsl":"","voy":"","lst_vsl":"JESN","lst_voy":"026B8W","lst_route":"AIMT","booking_date":"2026년 6월 27일","booking_schedule":"2026년 6월 27일","cancel_date":"","week_start_date":"2026년 06월 21일","lead_time_bkg_sche":"Week of Sailing (WOS)","yyyymm_bkg_sche":"202606","lst_status":"Waiting","fst_teu":2.0,"lst_teu":2.0,"norm_lst_teu":0.0,"cm1":0.0,"norm_cm1":0.0,"cm1_per_teu":0.0,"grade":"","route_profit":"","shipper_profit_tag":"","is_w3":false,"is_hi":false,"is_route_hi":false,"is_normal":false,"is_lifted":false,"is_cancel":false},{"bkg_no":"CN06790468","shipper_no":"","shipper_name":"","pol":"","pod_country":"","pod":"","dly_country":"AE","dly_plc":"KLF","vsl":"","voy":"","lst_vsl":"JESN","lst_voy":"026B8W","lst_route":"AIMT","booking_date":"2026년 6월 27일","booking_schedule":"2026년 6월 27일","cancel_date":"","week_start_date":"2026년 06월 21일","lead_time_bkg_sche":"Week of Sailing (WOS)","yyyymm_bkg_sche":"202606","lst_status":"Waiting","fst_teu":2.0,"lst_teu":2.0,"norm_lst_teu":0.0,"cm1":0.0,"norm_cm1":0.0,"cm1_per_teu":0.0,"grade":"","route_profit":"","shipper_profit_tag":"","is_w3":false,"is_hi":false,"is_route_hi":false,"is_normal":false,"is_lifted":false,"is_cancel":false},{"bkg_no":"CN06794405","shipper_no":"","shipper_name":"","pol":"","pod_country":"","pod":"","dly_country":"ID","dly_plc":"SRG","vsl":"","voy":"","lst_vsl":"JNGS","lst_voy":"0052S","lst_route":"KCS2","booking_date":"2026년 7월 1일","booking_schedule":"2026년 7월 1일","cancel_date":"","week_start_date":"2026년 06월 28일","lead_time_bkg_sche":"Week of Sailing (WOS)","yyyymm_bkg_sche":"202606","lst_status":"Normal","fst_teu":6.0,"lst_teu":6.0,"norm_lst_teu":6.0,"cm1":3054.0,"norm_cm1":3054.0,"cm1_per_teu":509.0,"grade":"","route_profit":"고수익","shipper_profit_tag":"","is_w3":false,"is_hi":true,"is_route_hi":true,"is_normal":true,"is_lifted":true,"is_cancel":false},{"bkg_no":"CN06797113","shipper_no":"","shipper_name":"","pol":"","pod_country":"","pod":"","dly_country":"ID","dly_plc":"SUB","vsl":"","voy":"","lst_vsl":"JNGS","lst_voy":"0052S","lst_route":"KCS2","booking_date":"2026년 6월 30일","booking_schedule":"2026년 6월 30일","cancel_date":"","week_start_date":"2026년 06월 28일","lead_time_bkg_sche":"Week of Sailing (WOS)","yyyymm_bkg_sche":"202606","lst_status":"Waiting","fst_teu":2.0,"lst_teu":2.0,"norm_lst_teu":0.0,"cm1":876.0,"norm_cm1":0.0,"cm1_per_teu":438.0,"grade":"","route_profit":"","shipper_profit_tag":"","is_w3":false,"is_hi":false,"is_route_hi":false,"is_normal":false,"is_lifted":false,"is_cancel":false},{"bkg_no":"CN06797128","shipper_no":"","shipper_name":"","pol":"","pod_country":"","pod":"","dly_country":"ID","dly_plc":"SUB","vsl":"","voy":"","lst_vsl":"JNGS","lst_voy":"0052S","lst_route":"KCS2","booking_date":"2026년 6월 30일","booking_schedule":"2026년 6월 30일","cancel_date":"","week_start_date":"2026년 06월 28일","lead_time_bkg_sche":"Week of Sailing (WOS)","yyyymm_bkg_sche":"202606","lst_status":"Waiting","fst_teu":2.0,"lst_teu":2.0,"norm_lst_teu":0.0,"cm1":876.0,"norm_cm1":0.0,"cm1_per_teu":438.0,"grade":"","route_profit":"","shipper_profit_tag":"","is_w3":false,"is_hi":false,"is_route_hi":false,"is_normal":false,"is_lifted":false,"is_cancel":false},{"bkg_no":"CN06801319","shipper_no":"","shipper_name":"","pol":"","pod_country":"","pod":"","dly_country":"OM","dly_plc":"SOH","vsl":"","voy":"","lst_vsl":"JESN","lst_voy":"026B8W","lst_route":"AIMT","booking_date":"2026년 6월 27일","booking_schedule":"2026년 6월 27일","cancel_date":"","week_start_date":"2026년 06월 21일","lead_time_bkg_sche":"Week of Sailing (WOS)","yyyymm_bkg_sche":"202606","lst_status":"Waiting","fst_teu":2.0,"lst_teu":2.0,"norm_lst_teu":0.0,"cm1":4942.0,"norm_cm1":0.0,"cm1_per_teu":2471.0,"grade":"","route_profit":"","shipper_profit_tag":"","is_w3":false,"is_hi":false,"is_route_hi":false,"is_normal":false,"is_lifted":false,"is_cancel":false},{"bkg_no":"CN06802415","shipper_no":"","shipper_name":"","pol":"","pod_country":"","pod":"","dly_country":"AE","dly_plc":"KLF","vsl":"","voy":"","lst_vsl":"JESN","lst_voy":"026B8W","lst_route":"AIMT","booking_date":"2026년 6월 27일","booking_schedule":"2026년 6월 27일","cancel_date":"","week_start_date":"2026년 06월 21일","lead_time_bkg_sche":"Week of Sailing (WOS)","yyyymm_bkg_sche":"202606","lst_status":"Waiting","fst_teu":2.0,"lst_teu":2.0,"norm_lst_teu":0.0,"cm1":4198.0,"norm_cm1":0.0,"cm1_per_teu":2099.0,"grade":"","route_profit":"","shipper_profit_tag":"","is_w3":false,"is_hi":false,"is_route_hi":false,"is_normal":false,"is_lifted":false,"is_cancel":false},{"bkg_no":"CN06802607","shipper_no":"","shipper_name":"","pol":"","pod_country":"","pod":"","dly_country":"AE","dly_plc":"KLF","vsl":"","voy":"","lst_vsl":"JESN","lst_voy":"026B8W","lst_route":"AIMT","booking_date":"2026년 6월 27일","booking_schedule":"2026년 6월 27일","cancel_date":"","week_start_date":"2026년 06월 21일","lead_time_bkg_sche":"Week of Sailing (WOS)","yyyymm_bkg_sche":"202606","lst_status":"Waiting","fst_teu":2.0,"lst_teu":2.0,"norm_lst_teu":0.0,"cm1":0.0,"norm_cm1":0.0,"cm1_per_teu":0.0,"grade":"","route_profit":"","shipper_profit_tag":"","is_w3":false,"is_hi":false,"is_route_hi":false,"is_normal":false,"is_lifted":false,"is_cancel":false},{"bkg_no":"CN06802612","shipper_no":"","shipper_name":"","pol":"","pod_country":"","pod":"","dly_country":"OM","dly_plc":"SOH","vsl":"","voy":"","lst_vsl":"JESN","lst_voy":"026B8W","lst_route":"AIMT","booking_date":"2026년 6월 27일","booking_schedule":"2026년 6월 27일","cancel_date":"","week_start_date":"2026년 06월 21일","lead_time_bkg_sche":"Week of Sailing (WOS)","yyyymm_bkg_sche":"202606","lst_status":"Waiting","fst_teu":2.0,"lst_teu":2.0,"norm_lst_teu":0.0,"cm1":5222.0,"norm_cm1":0.0,"cm1_per_teu":2611.0,"grade":"","route_profit":"","shipper_profit_tag":"","is_w3":false,"is_hi":false,"is_route_hi":false,"is_normal":false,"is_lifted":false,"is_cancel":false},{"bkg_no":"CN06802613","shipper_no":"","shipper_name":"","pol":"","pod_country":"","pod":"","dly_country":"OM","dly_plc":"SOH","vsl":"","voy":"","lst_vsl":"JESN","lst_voy":"026B8W","lst_route":"AIMT","booking_date":"2026년 6월 27일","booking_schedule":"2026년 6월 27일","cancel_date":"","week_start_date":"2026년 06월 21일","lead_time_bkg_sche":"Week of Sailing (WOS)","yyyymm_bkg_sche":"202606","lst_status":"Waiting","fst_teu":2.0,"lst_teu":2.0,"norm_lst_teu":0.0,"cm1":5222.0,"norm_cm1":0.0,"cm1_per_teu":2611.0,"grade":"","route_profit":"","shipper_profit_tag":"","is_w3":false,"is_hi":false,"is_route_hi":false,"is_normal":false,"is_lifted":false,"is_cancel":false},{"bkg_no":"CN06802616","shipper_no":"","shipper_name":"","pol":"","pod_country":"","pod":"","dly_country":"OM","dly_plc":"SOH","vsl":"","voy":"","lst_vsl":"JESN","lst_voy":"026B8W","lst_route":"AIMT","booking_date":"2026년 6월 27일","booking_schedule":"2026년 6월 27일","cancel_date":"","week_start_date":"2026년 06월 21일","lead_time_bkg_sche":"Week of Sailing (WOS)","yyyymm_bkg_sche":"202606","lst_status":"Waiting","fst_teu":2.0,"lst_teu":2.0,"norm_lst_teu":0.0,"cm1":5222.0,"norm_cm1":0.0,"cm1_per_teu":2611.0,"grade":"","route_profit":"","shipper_profit_tag":"","is_w3":false,"is_hi":false,"is_route_hi":false,"is_normal":false,"is_lifted":false,"is_cancel":false},{"bkg_no":"CN06802623","shipper_no":"","shipper_name":"","pol":"","pod_country":"","pod":"","dly_country":"AE","dly_plc":"KLF","vsl":"","voy":"","lst_vsl":"JESN","lst_voy":"026B8W","lst_route":"AIMT","booking_date":"2026년 6월 27일","booking_schedule":"2026년 6월 27일","cancel_date":"","week_start_date":"2026년 06월 21일","lead_time_bkg_sche":"Week of Sailing (WOS)","yyyymm_bkg_sche":"202606","lst_status":"Waiting","fst_teu":2.0,"lst_teu":2.0,"norm_lst_teu":0.0,"cm1":0.0,"norm_cm1":0.0,"cm1_per_teu":0.0,"grade":"","route_profit":"","shipper_profit_tag":"","is_w3":false,"is_hi":false,"is_route_hi":false,"is_normal":false,"is_lifted":false,"is_cancel":false},{"bkg_no":"CN06802627","shipper_no":"","shipper_name":"","pol":"","pod_country":"","pod":"","dly_country":"AE","dly_plc":"KLF","vsl":"","voy":"","lst_vsl":"JESN","lst_voy":"026B8W","lst_route":"AIMT","booking_date":"2026년 6월 27일","booking_schedule":"2026년 6월 27일","cancel_date":"","week_start_date":"2026년 06월 21일","lead_time_bkg_sche":"Week of Sailing (WOS)","yyyymm_bkg_sche":"202606","lst_status":"Waiting","fst_teu":2.0,"lst_teu":2.0,"norm_lst_teu":0.0,"cm1":0.0,"norm_cm1":0.0,"cm1_per_teu":0.0,"grade":"","route_profit":"","shipper_profit_tag":"","is_w3":false,"is_hi":false,"is_route_hi":false,"is_normal":false,"is_lifted":false,"is_cancel":false},{"bkg_no":"CN06802629","shipper_no":"","shipper_name":"","pol":"","pod_country":"","pod":"","dly_country":"AE","dly_plc":"KLF","vsl":"","voy":"","lst_vsl":"JEWS","lst_voy":"026B7W","lst_route":"AIMT","booking_date":"2026년 7월 1일","booking_schedule":"2026년 7월 1일","cancel_date":"","week_start_date":"2026년 06월 28일","lead_time_bkg_sche":"Week of Sailing (WOS)","yyyymm_bkg_sche":"202606","lst_status":"Waiting","fst_teu":2.0,"lst_teu":2.0,"norm_lst_teu":0.0,"cm1":0.0,"norm_cm1":0.0,"cm1_per_teu":0.0,"grade":"","route_profit":"","shipper_profit_tag":"","is_w3":false,"is_hi":false,"is_route_hi":false,"is_normal":false,"is_lifted":false,"is_cancel":false},{"bkg_no":"CN06802633","shipper_no":"","shipper_name":"","pol":"","pod_country":"","pod":"","dly_country":"AE","dly_plc":"KLF","vsl":"","voy":"","lst_vsl":"JESN","lst_voy":"026B8W","lst_route":"AIMT","booking_date":"2026년 6월 27일","booking_schedule":"2026년 6월 27일","cancel_date":"","week_start_date":"2026년 06월 21일","lead_time_bkg_sche":"Week of Sailing (WOS)","yyyymm_bkg_sche":"202606","lst_status":"Waiting","fst_teu":2.0,"lst_teu":2.0,"norm_lst_teu":0.0,"cm1":0.0,"norm_cm1":0.0,"cm1_per_teu":0.0,"grade":"","route_profit":"","shipper_profit_tag":"","is_w3":false,"is_hi":false,"is_route_hi":false,"is_normal":false,"is_lifted":false,"is_cancel":false},{"bkg_no":"CN06802635","shipper_no":"","shipper_name":"","pol":"","pod_country":"","pod":"","dly_country":"AE","dly_plc":"KLF","vsl":"","voy":"","lst_vsl":"JESN","lst_voy":"026B8W","lst_route":"AIMT","booking_date":"2026년 6월 27일","booking_schedule":"2026년 6월 27일","cancel_date":"","week_start_date":"2026년 06월 21일","lead_time_bkg_sche":"Week of Sailing (WOS)","yyyymm_bkg_sche":"202606","lst_status":"Waiting","fst_teu":2.0,"lst_teu":2.0,"norm_lst_teu":0.0,"cm1":0.0,"norm_cm1":0.0,"cm1_per_teu":0.0,"grade":"","route_profit":"","shipper_profit_tag":"","is_w3":false,"is_hi":false,"is_route_hi":false,"is_normal":false,"is_lifted":false,"is_cancel":false},{"bkg_no":"CN06802640","shipper_no":"","shipper_name":"","pol":"","pod_country":"","pod":"","dly_country":"AE","dly_plc":"KLF","vsl":"","voy":"","lst_vsl":"JEWS","lst_voy":"026B7W","lst_route":"AIMT","booking_date":"2026년 7월 1일","booking_schedule":"2026년 7월 1일","cancel_date":"","week_start_date":"2026년 06월 28일","lead_time_bkg_sche":"Week of Sailing (WOS)","yyyymm_bkg_sche":"202606","lst_status":"Waiting","fst_teu":2.0,"lst_teu":2.0,"norm_lst_teu":0.0,"cm1":0.0,"norm_cm1":0.0,"cm1_per_teu":0.0,"grade":"","route_profit":"","shipper_profit_tag":"","is_w3":false,"is_hi":false,"is_route_hi":false,"is_normal":false,"is_lifted":false,"is_cancel":false},{"bkg_no":"CN06802645","shipper_no":"","shipper_name":"","pol":"","pod_country":"","pod":"","dly_country":"AE","dly_plc":"KLF","vsl":"","voy":"","lst_vsl":"JEWS","lst_voy":"026B7W","lst_route":"AIMT","booking_date":"2026년 7월 1일","booking_schedule":"2026년 7월 1일","cancel_date":"","week_start_date":"2026년 06월 28일","lead_time_bkg_sche":"Week of Sailing (WOS)","yyyymm_bkg_sche":"202606","lst_status":"Waiting","fst_teu":2.0,"lst_teu":2.0,"norm_lst_teu":0.0,"cm1":0.0,"norm_cm1":0.0,"cm1_per_teu":0.0,"grade":"","route_profit":"","shipper_profit_tag":"","is_w3":false,"is_hi":false,"is_route_hi":false,"is_normal":false,"is_lifted":false,"is_cancel":false},{"bkg_no":"CN06802697","shipper_no":"","shipper_name":"","pol":"","pod_country":"","pod":"","dly_country":"OM","dly_plc":"SOH","vsl":"","voy":"","lst_vsl":"JESN","lst_voy":"026B8W","lst_route":"AIMT","booking_date":"2026년 6월 27일","booking_schedule":"2026년 6월 27일","cancel_date":"","week_start_date":"2026년 06월 21일","lead_time_bkg_sche":"Week of Sailing (WOS)","yyyymm_bkg_sche":"202606","lst_status":"Waiting","fst_teu":2.0,"lst_teu":2.0,"norm_lst_teu":0.0,"cm1":5190.0,"norm_cm1":0.0,"cm1_per_teu":2595.0,"grade":"","route_profit":"","shipper_profit_tag":"","is_w3":false,"is_hi":false,"is_route_hi":false,"is_normal":false,"is_lifted":false,"is_cancel":false},{"bkg_no":"CN06802699","shipper_no":"","shipper_name":"","pol":"","pod_country":"","pod":"","dly_country":"OM","dly_plc":"SOH","vsl":"","voy":"","lst_vsl":"JESN","lst_voy":"026B8W","lst_route":"AIMT","booking_date":"2026년 6월 27일","booking_schedule":"2026년 6월 27일","cancel_date":"","week_start_date":"2026년 06월 21일","lead_time_bkg_sche":"Week of Sailing (WOS)","yyyymm_bkg_sche":"202606","lst_status":"Waiting","fst_teu":2.0,"lst_teu":2.0,"norm_lst_teu":0.0,"cm1":5190.0,"norm_cm1":0.0,"cm1_per_teu":2595.0,"grade":"","route_profit":"","shipper_profit_tag":"","is_w3":false,"is_hi":false,"is_route_hi":false,"is_normal":false,"is_lifted":false,"is_cancel":false},{"bkg_no":"CN06802701","shipper_no":"","shipper_name":"","pol":"","pod_country":"","pod":"","dly_country":"OM","dly_plc":"SOH","vsl":"","voy":"","lst_vsl":"JESN","lst_voy":"026B8W","lst_route":"AIMT","booking_date":"2026년 6월 27일","booking_schedule":"2026년 6월 27일","cancel_date":"","week_start_date":"2026년 06월 21일","lead_time_bkg_sche":"Week of Sailing (WOS)","yyyymm_bkg_sche":"202606","lst_status":"Waiting","fst_teu":2.0,"lst_teu":2.0,"norm_lst_teu":0.0,"cm1":5190.0,"norm_cm1":0.0,"cm1_per_teu":2595.0,"grade":"","route_profit":"","shipper_profit_tag":"","is_w3":false,"is_hi":false,"is_route_hi":false,"is_normal":false,"is_lifted":false,"is_cancel":false},{"bkg_no":"CN06802703","shipper_no":"","shipper_name":"","pol":"","pod_country":"","pod":"","dly_country":"OM","dly_plc":"SOH","vsl":"","voy":"","lst_vsl":"JESN","lst_voy":"026B8W","lst_route":"AIMT","booking_date":"2026년 6월 27일","booking_schedule":"2026년 6월 27일","cancel_date":"","week_start_date":"2026년 06월 21일","lead_time_bkg_sche":"Week of Sailing (WOS)","yyyymm_bkg_sche":"202606","lst_status":"Waiting","fst_teu":2.0,"lst_teu":2.0,"norm_lst_teu":0.0,"cm1":5190.0,"norm_cm1":0.0,"cm1_per_teu":2595.0,"grade":"","route_profit":"","shipper_profit_tag":"","is_w3":false,"is_hi":false,"is_route_hi":false,"is_normal":false,"is_lifted":false,"is_cancel":false},{"bkg_no":"CN06803702","shipper_no":"","shipper_name":"","pol":"","pod_country":"","pod":"","dly_country":"AE","dly_plc":"KLF","vsl":"","voy":"","lst_vsl":"JEWS","lst_voy":"026B7W","lst_route":"AIMT","booking_date":"2026년 7월 1일","booking_schedule":"2026년 7월 1일","cancel_date":"","week_start_date":"2026년 06월 28일","lead_time_bkg_sche":"Week of Sailing (WOS)","yyyymm_bkg_sche":"202606","lst_status":"Waiting","fst_teu":2.0,"lst_teu":2.0,"norm_lst_teu":0.0,"cm1":0.0,"norm_cm1":0.0,"cm1_per_teu":0.0,"grade":"","route_profit":"","shipper_profit_tag":"","is_w3":false,"is_hi":false,"is_route_hi":false,"is_normal":false,"is_lifted":false,"is_cancel":false},{"bkg_no":"CN06803715","shipper_no":"","shipper_name":"","pol":"","pod_country":"","pod":"","dly_country":"AE","dly_plc":"KLF","vsl":"","voy":"","lst_vsl":"JEWS","lst_voy":"026B7W","lst_route":"AIMT","booking_date":"2026년 7월 1일","booking_schedule":"2026년 7월 1일","cancel_date":"","week_start_date":"2026년 06월 28일","lead_time_bkg_sche":"Week of Sailing (WOS)","yyyymm_bkg_sche":"202606","lst_status":"Waiting","fst_teu":2.0,"lst_teu":2.0,"norm_lst_teu":0.0,"cm1":0.0,"norm_cm1":0.0,"cm1_per_teu":0.0,"grade":"","route_profit":"","shipper_profit_tag":"","is_w3":false,"is_hi":false,"is_route_hi":false,"is_normal":false,"is_lifted":false,"is_cancel":false},{"bkg_no":"CN06803729","shipper_no":"","shipper_name":"","pol":"","pod_country":"","pod":"","dly_country":"AE","dly_plc":"KLF","vsl":"","voy":"","lst_vsl":"JEWS","lst_voy":"026B7W","lst_route":"AIMT","booking_date":"2026년 7월 1일","booking_schedule":"2026년 7월 1일","cancel_date":"","week_start_date":"2026년 06월 28일","lead_time_bkg_sche":"Week of Sailing (WOS)","yyyymm_bkg_sche":"202606","lst_status":"Waiting","fst_teu":2.0,"lst_teu":2.0,"norm_lst_teu":0.0,"cm1":0.0,"norm_cm1":0.0,"cm1_per_teu":0.0,"grade":"","route_profit":"","shipper_profit_tag":"","is_w3":false,"is_hi":false,"is_route_hi":false,"is_normal":false,"is_lifted":false,"is_cancel":false},{"bkg_no":"CN06803743","shipper_no":"","shipper_name":"","pol":"","pod_country":"","pod":"","dly_country":"AE","dly_plc":"KLF","vsl":"","voy":"","lst_vsl":"JEWS","lst_voy":"026B7W","lst_route":"AIMT","booking_date":"2026년 7월 1일","booking_schedule":"2026년 7월 1일","cancel_date":"","week_start_date":"2026년 06월 28일","lead_time_bkg_sche":"Week of Sailing (WOS)","yyyymm_bkg_sche":"202606","lst_status":"Waiting","fst_teu":2.0,"lst_teu":2.0,"norm_lst_teu":0.0,"cm1":0.0,"norm_cm1":0.0,"cm1_per_teu":0.0,"grade":"","route_profit":"","shipper_profit_tag":"","is_w3":false,"is_hi":false,"is_route_hi":false,"is_normal":false,"is_lifted":false,"is_cancel":false},{"bkg_no":"CN06803903","shipper_no":"","shipper_name":"","pol":"","pod_country":"","pod":"","dly_country":"OM","dly_plc":"SOH","vsl":"","voy":"","lst_vsl":"JEWS","lst_voy":"026B7W","lst_route":"AIMT","booking_date":"2026년 7월 1일","booking_schedule":"2026년 7월 1일","cancel_date":"","week_start_date":"2026년 06월 28일","lead_time_bkg_sche":"Week of Sailing (WOS)","yyyymm_bkg_sche":"202606","lst_status":"Waiting","fst_teu":2.0,"lst_teu":2.0,"norm_lst_teu":0.0,"cm1":5190.0,"norm_cm1":0.0,"cm1_per_teu":2595.0,"grade":"","route_profit":"","shipper_profit_tag":"","is_w3":false,"is_hi":false,"is_route_hi":false,"is_normal":false,"is_lifted":false,"is_cancel":false},{"bkg_no":"CN06803937","shipper_no":"","shipper_name":"","pol":"","pod_country":"","pod":"","dly_country":"OM","dly_plc":"SOH","vsl":"","voy":"","lst_vsl":"JEWS","lst_voy":"026B7W","lst_route":"AIMT","booking_date":"2026년 7월 1일","booking_schedule":"2026년 7월 1일","cancel_date":"","week_start_date":"2026년 06월 28일","lead_time_bkg_sche":"Week of Sailing (WOS)","yyyymm_bkg_sche":"202606","lst_status":"Waiting","fst_teu":2.0,"lst_teu":2.0,"norm_lst_teu":0.0,"cm1":5190.0,"norm_cm1":0.0,"cm1_per_teu":2595.0,"grade":"","route_profit":"","shipper_profit_tag":"","is_w3":false,"is_hi":false,"is_route_hi":false,"is_normal":false,"is_lifted":false,"is_cancel":false},{"bkg_no":"CN06804107","shipper_no":"","shipper_name":"","pol":"","pod_country":"","pod":"","dly_country":"AE","dly_plc":"KLF","vsl":"","voy":"","lst_vsl":"JESN","lst_voy":"026B8W","lst_route":"AIMT","booking_date":"2026년 6월 27일","booking_schedule":"2026년 6월 27일","cancel_date":"","week_start_date":"2026년 06월 21일","lead_time_bkg_sche":"Week of Sailing (WOS)","yyyymm_bkg_sche":"202606","lst_status":"Waiting","fst_teu":2.0,"lst_teu":2.0,"norm_lst_teu":0.0,"cm1":0.0,"norm_cm1":0.0,"cm1_per_teu":0.0,"grade":"","route_profit":"","shipper_profit_tag":"","is_w3":false,"is_hi":false,"is_route_hi":false,"is_normal":false,"is_lifted":false,"is_cancel":false},{"bkg_no":"CN06804119","shipper_no":"","shipper_name":"","pol":"","pod_country":"","pod":"","dly_country":"AE","dly_plc":"KLF","vsl":"","voy":"","lst_vsl":"JESN","lst_voy":"026B8W","lst_route":"AIMT","booking_date":"2026년 6월 27일","booking_schedule":"2026년 6월 27일","cancel_date":"","week_start_date":"2026년 06월 21일","lead_time_bkg_sche":"Week of Sailing (WOS)","yyyymm_bkg_sche":"202606","lst_status":"Waiting","fst_teu":2.0,"lst_teu":2.0,"norm_lst_teu":0.0,"cm1":0.0,"norm_cm1":0.0,"cm1_per_teu":0.0,"grade":"","route_profit":"","shipper_profit_tag":"","is_w3":false,"is_hi":false,"is_route_hi":false,"is_normal":false,"is_lifted":false,"is_cancel":false},{"bkg_no":"CN06804129","shipper_no":"","shipper_name":"","pol":"","pod_country":"","pod":"","dly_country":"AE","dly_plc":"KLF","vsl":"","voy":"","lst_vsl":"JESN","lst_voy":"026B8W","lst_route":"AIMT","booking_date":"2026년 6월 27일","booking_schedule":"2026년 6월 27일","cancel_date":"","week_start_date":"2026년 06월 21일","lead_time_bkg_sche":"Week of Sailing (WOS)","yyyymm_bkg_sche":"202606","lst_status":"Waiting","fst_teu":2.0,"lst_teu":2.0,"norm_lst_teu":0.0,"cm1":0.0,"norm_cm1":0.0,"cm1_per_teu":0.0,"grade":"","route_profit":"","shipper_profit_tag":"","is_w3":false,"is_hi":false,"is_route_hi":false,"is_normal":false,"is_lifted":false,"is_cancel":false},{"bkg_no":"CN06807081","shipper_no":"","shipper_name":"","pol":"","pod_country":"","pod":"","dly_country":"AE","dly_plc":"KLF","vsl":"","voy":"","lst_vsl":"JESN","lst_voy":"026B8W","lst_route":"AIMT","booking_date":"2026년 6월 27일","booking_schedule":"2026년 6월 27일","cancel_date":"","week_start_date":"2026년 06월 21일","lead_time_bkg_sche":"Week of Sailing (WOS)","yyyymm_bkg_sche":"202606","lst_status":"Waiting","fst_teu":2.0,"lst_teu":2.0,"norm_lst_teu":0.0,"cm1":4628.0,"norm_cm1":0.0,"cm1_per_teu":2314.0,"grade":"","route_profit":"","shipper_profit_tag":"","is_w3":false,"is_hi":false,"is_route_hi":false,"is_normal":false,"is_lifted":false,"is_cancel":false},{"bkg_no":"CN06807100","shipper_no":"","shipper_name":"","pol":"","pod_country":"","pod":"","dly_country":"AE","dly_plc":"KLF","vsl":"","voy":"","lst_vsl":"JESN","lst_voy":"026B8W","lst_route":"AIMT","booking_date":"2026년 6월 27일","booking_schedule":"2026년 6월 27일","cancel_date":"","week_start_date":"2026년 06월 21일","lead_time_bkg_sche":"Week of Sailing (WOS)","yyyymm_bkg_sche":"202606","lst_status":"Waiting","fst_teu":2.0,"lst_teu":2.0,"norm_lst_teu":0.0,"cm1":4628.0,"norm_cm1":0.0,"cm1_per_teu":2314.0,"grade":"","route_profit":"","shipper_profit_tag":"","is_w3":false,"is_hi":false,"is_route_hi":false,"is_normal":false,"is_lifted":false,"is_cancel":false},{"bkg_no":"CN06807422","shipper_no":"","shipper_name":"","pol":"","pod_country":"","pod":"","dly_country":"ID","dly_plc":"JKT","vsl":"","voy":"","lst_vsl":"JNGS","lst_voy":"0052S","lst_route":"KCS2","booking_date":"2026년 6월 30일","booking_schedule":"2026년 6월 30일","cancel_date":"","week_start_date":"2026년 06월 28일","lead_time_bkg_sche":"Week of Sailing (WOS)","yyyymm_bkg_sche":"202606","lst_status":"Waiting","fst_teu":2.0,"lst_teu":2.0,"norm_lst_teu":0.0,"cm1":976.0,"norm_cm1":0.0,"cm1_per_teu":488.0,"grade":"","route_profit":"고수익","shipper_profit_tag":"","is_w3":false,"is_hi":true,"is_route_hi":true,"is_normal":false,"is_lifted":false,"is_cancel":false},{"bkg_no":"CN06807430","shipper_no":"","shipper_name":"","pol":"","pod_country":"","pod":"","dly_country":"ID","dly_plc":"JKT","vsl":"","voy":"","lst_vsl":"JNGS","lst_voy":"0052S","lst_route":"KCS2","booking_date":"2026년 6월 30일","booking_schedule":"2026년 6월 30일","cancel_date":"","week_start_date":"2026년 06월 28일","lead_time_bkg_sche":"Week of Sailing (WOS)","yyyymm_bkg_sche":"202606","lst_status":"Waiting","fst_teu":2.0,"lst_teu":2.0,"norm_lst_teu":0.0,"cm1":976.0,"norm_cm1":0.0,"cm1_per_teu":488.0,"grade":"","route_profit":"고수익","shipper_profit_tag":"","is_w3":false,"is_hi":true,"is_route_hi":true,"is_normal":false,"is_lifted":false,"is_cancel":false},{"bkg_no":"CN06807434","shipper_no":"","shipper_name":"","pol":"","pod_country":"","pod":"","dly_country":"ID","dly_plc":"SUB","vsl":"","voy":"","lst_vsl":"JNGS","lst_voy":"0052S","lst_route":"KCS2","booking_date":"2026년 6월 30일","booking_schedule":"2026년 6월 30일","cancel_date":"","week_start_date":"2026년 06월 28일","lead_time_bkg_sche":"Week of Sailing (WOS)","yyyymm_bkg_sche":"202606","lst_status":"Waiting","fst_teu":1.0,"lst_teu":1.0,"norm_lst_teu":0.0,"cm1":583.0,"norm_cm1":0.0,"cm1_per_teu":583.0,"grade":"","route_profit":"","shipper_profit_tag":"","is_w3":false,"is_hi":false,"is_route_hi":false,"is_normal":false,"is_lifted":false,"is_cancel":false},{"bkg_no":"CN06809853","shipper_no":"","shipper_name":"","pol":"","pod_country":"","pod":"","dly_country":"OM","dly_plc":"SOH","vsl":"","voy":"","lst_vsl":"JESN","lst_voy":"026B8W","lst_route":"AIMT","booking_date":"2026년 6월 27일","booking_schedule":"2026년 6월 27일","cancel_date":"","week_start_date":"2026년 06월 21일","lead_time_bkg_sche":"Week of Sailing (WOS)","yyyymm_bkg_sche":"202606","lst_status":"Waiting","fst_teu":2.0,"lst_teu":2.0,"norm_lst_teu":0.0,"cm1":4942.0,"norm_cm1":0.0,"cm1_per_teu":2471.0,"grade":"","route_profit":"","shipper_profit_tag":"","is_w3":false,"is_hi":false,"is_route_hi":false,"is_normal":false,"is_lifted":false,"is_cancel":false},{"bkg_no":"CN06811620","shipper_no":"","shipper_name":"","pol":"","pod_country":"","pod":"","dly_country":"OM","dly_plc":"SOH","vsl":"","voy":"","lst_vsl":"JESN","lst_voy":"026B8W","lst_route":"AIMT","booking_date":"2026년 6월 27일","booking_schedule":"2026년 6월 27일","cancel_date":"","week_start_date":"2026년 06월 21일","lead_time_bkg_sche":"Week of Sailing (WOS)","yyyymm_bkg_sche":"202606","lst_status":"Waiting","fst_teu":2.0,"lst_teu":2.0,"norm_lst_teu":0.0,"cm1":5222.0,"norm_cm1":0.0,"cm1_per_teu":2611.0,"grade":"","route_profit":"","shipper_profit_tag":"","is_w3":false,"is_hi":false,"is_route_hi":false,"is_normal":false,"is_lifted":false,"is_cancel":false},{"bkg_no":"CN06811890","shipper_no":"","shipper_name":"","pol":"","pod_country":"","pod":"","dly_country":"TZ","dly_plc":"DAR","vsl":"","voy":"","lst_vsl":"JTTC","lst_voy":"2603W","lst_route":"EAX","booking_date":"2026년 7월 1일","booking_schedule":"2026년 7월 1일","cancel_date":"","week_start_date":"2026년 06월 28일","lead_time_bkg_sche":"Week of Sailing (WOS)","yyyymm_bkg_sche":"202606","lst_status":"Waiting","fst_teu":2.0,"lst_teu":2.0,"norm_lst_teu":0.0,"cm1":2054.0,"norm_cm1":0.0,"cm1_per_teu":1027.0,"grade":"","route_profit":"","shipper_profit_tag":"","is_w3":false,"is_hi":false,"is_route_hi":false,"is_normal":false,"is_lifted":false,"is_cancel":false},{"bkg_no":"CN06811892","shipper_no":"","shipper_name":"","pol":"","pod_country":"","pod":"","dly_country":"TZ","dly_plc":"DAR","vsl":"","voy":"","lst_vsl":"JTTC","lst_voy":"2603W","lst_route":"EAX","booking_date":"2026년 7월 1일","booking_schedule":"2026년 7월 1일","cancel_date":"","week_start_date":"2026년 06월 28일","lead_time_bkg_sche":"Week of Sailing (WOS)","yyyymm_bkg_sche":"202606","lst_status":"Waiting","fst_teu":2.0,"lst_teu":2.0,"norm_lst_teu":0.0,"cm1":2054.0,"norm_cm1":0.0,"cm1_per_teu":1027.0,"grade":"","route_profit":"","shipper_profit_tag":"","is_w3":false,"is_hi":false,"is_route_hi":false,"is_normal":false,"is_lifted":false,"is_cancel":false},{"bkg_no":"CN06811895","shipper_no":"","shipper_name":"","pol":"","pod_country":"","pod":"","dly_country":"TZ","dly_plc":"DAR","vsl":"","voy":"","lst_vsl":"JTTC","lst_voy":"2603W","lst_route":"EAX","booking_date":"2026년 7월 1일","booking_schedule":"2026년 7월 1일","cancel_date":"","week_start_date":"2026년 06월 28일","lead_time_bkg_sche":"Week of Sailing (WOS)","yyyymm_bkg_sche":"202606","lst_status":"Waiting","fst_teu":2.0,"lst_teu":2.0,"norm_lst_teu":0.0,"cm1":2054.0,"norm_cm1":0.0,"cm1_per_teu":1027.0,"grade":"","route_profit":"","shipper_profit_tag":"","is_w3":false,"is_hi":false,"is_route_hi":false,"is_normal":false,"is_lifted":false,"is_cancel":false},{"bkg_no":"CN06811898","shipper_no":"","shipper_name":"","pol":"","pod_country":"","pod":"","dly_country":"TZ","dly_plc":"DAR","vsl":"","voy":"","lst_vsl":"JTTC","lst_voy":"2603W","lst_route":"EAX","booking_date":"2026년 7월 1일","booking_schedule":"2026년 7월 1일","cancel_date":"","week_start_date":"2026년 06월 28일","lead_time_bkg_sche":"Week of Sailing (WOS)","yyyymm_bkg_sche":"202606","lst_status":"Waiting","fst_teu":2.0,"lst_teu":2.0,"norm_lst_teu":0.0,"cm1":2054.0,"norm_cm1":0.0,"cm1_per_teu":1027.0,"grade":"","route_profit":"","shipper_profit_tag":"","is_w3":false,"is_hi":false,"is_route_hi":false,"is_normal":false,"is_lifted":false,"is_cancel":false},{"bkg_no":"CN06811902","shipper_no":"","shipper_name":"","pol":"","pod_country":"","pod":"","dly_country":"TZ","dly_plc":"DAR","vsl":"","voy":"","lst_vsl":"JTTC","lst_voy":"2603W","lst_route":"EAX","booking_date":"2026년 7월 1일","booking_schedule":"2026년 7월 1일","cancel_date":"","week_start_date":"2026년 06월 28일","lead_time_bkg_sche":"Week of Sailing (WOS)","yyyymm_bkg_sche":"202606","lst_status":"Waiting","fst_teu":2.0,"lst_teu":2.0,"norm_lst_teu":0.0,"cm1":2054.0,"norm_cm1":0.0,"cm1_per_teu":1027.0,"grade":"","route_profit":"","shipper_profit_tag":"","is_w3":false,"is_hi":false,"is_route_hi":false,"is_normal":false,"is_lifted":false,"is_cancel":false},{"bkg_no":"CN06811903","shipper_no":"","shipper_name":"","pol":"","pod_country":"","pod":"","dly_country":"TZ","dly_plc":"DAR","vsl":"","voy":"","lst_vsl":"JTTC","lst_voy":"2603W","lst_route":"EAX","booking_date":"2026년 7월 1일","booking_schedule":"2026년 7월 1일","cancel_date":"","week_start_date":"2026년 06월 28일","lead_time_bkg_sche":"Week of Sailing (WOS)","yyyymm_bkg_sche":"202606","lst_status":"Waiting","fst_teu":2.0,"lst_teu":2.0,"norm_lst_teu":0.0,"cm1":2054.0,"norm_cm1":0.0,"cm1_per_teu":1027.0,"grade":"","route_profit":"","shipper_profit_tag":"","is_w3":false,"is_hi":false,"is_route_hi":false,"is_normal":false,"is_lifted":false,"is_cancel":false},{"bkg_no":"CN06813352","shipper_no":"","shipper_name":"","pol":"","pod_country":"","pod":"","dly_country":"TZ","dly_plc":"DAR","vsl":"","voy":"","lst_vsl":"JTTC","lst_voy":"2603W","lst_route":"EAX","booking_date":"2026년 7월 1일","booking_schedule":"2026년 7월 1일","cancel_date":"","week_start_date":"2026년 06월 28일","lead_time_bkg_sche":"Week of Sailing (WOS)","yyyymm_bkg_sche":"202606","lst_status":"Waiting","fst_teu":2.0,"lst_teu":2.0,"norm_lst_teu":0.0,"cm1":2054.0,"norm_cm1":0.0,"cm1_per_teu":1027.0,"grade":"","route_profit":"","shipper_profit_tag":"","is_w3":false,"is_hi":false,"is_route_hi":false,"is_normal":false,"is_lifted":false,"is_cancel":false},{"bkg_no":"CN06813354","shipper_no":"","shipper_name":"","pol":"","pod_country":"","pod":"","dly_country":"TZ","dly_plc":"DAR","vsl":"","voy":"","lst_vsl":"JTTC","lst_voy":"2603W","lst_route":"EAX","booking_date":"2026년 7월 1일","booking_schedule":"2026년 7월 1일","cancel_date":"","week_start_date":"2026년 06월 28일","lead_time_bkg_sche":"Week of Sailing (WOS)","yyyymm_bkg_sche":"202606","lst_status":"Waiting","fst_teu":2.0,"lst_teu":2.0,"norm_lst_teu":0.0,"cm1":2054.0,"norm_cm1":0.0,"cm1_per_teu":1027.0,"grade":"","route_profit":"","shipper_profit_tag":"","is_w3":false,"is_hi":false,"is_route_hi":false,"is_normal":false,"is_lifted":false,"is_cancel":false},{"bkg_no":"CN06813358","shipper_no":"","shipper_name":"","pol":"","pod_country":"","pod":"","dly_country":"AE","dly_plc":"KLF","vsl":"","voy":"","lst_vsl":"JESN","lst_voy":"026B8W","lst_route":"AIMT","booking_date":"2026년 6월 27일","booking_schedule":"2026년 6월 27일","cancel_date":"","week_start_date":"2026년 06월 21일","lead_time_bkg_sche":"Week of Sailing (WOS)","yyyymm_bkg_sche":"202606","lst_status":"Waiting","fst_teu":2.0,"lst_teu":2.0,"norm_lst_teu":0.0,"cm1":0.0,"norm_cm1":0.0,"cm1_per_teu":0.0,"grade":"","route_profit":"","shipper_profit_tag":"","is_w3":false,"is_hi":false,"is_route_hi":false,"is_normal":false,"is_lifted":false,"is_cancel":false},{"bkg_no":"CN06813361","shipper_no":"","shipper_name":"","pol":"","pod_country":"","pod":"","dly_country":"AE","dly_plc":"KLF","vsl":"","voy":"","lst_vsl":"JESN","lst_voy":"026B8W","lst_route":"AIMT","booking_date":"2026년 6월 27일","booking_schedule":"2026년 6월 27일","cancel_date":"","week_start_date":"2026년 06월 21일","lead_time_bkg_sche":"Week of Sailing (WOS)","yyyymm_bkg_sche":"202606","lst_status":"Waiting","fst_teu":2.0,"lst_teu":2.0,"norm_lst_teu":0.0,"cm1":0.0,"norm_cm1":0.0,"cm1_per_teu":0.0,"grade":"","route_profit":"","shipper_profit_tag":"","is_w3":false,"is_hi":false,"is_route_hi":false,"is_normal":false,"is_lifted":false,"is_cancel":false},{"bkg_no":"CN06813363","shipper_no":"","shipper_name":"","pol":"","pod_country":"","pod":"","dly_country":"AE","dly_plc":"KLF","vsl":"","voy":"","lst_vsl":"JESN","lst_voy":"026B8W","lst_route":"AIMT","booking_date":"2026년 6월 27일","booking_schedule":"2026년 6월 27일","cancel_date":"","week_start_date":"2026년 06월 21일","lead_time_bkg_sche":"Week of Sailing (WOS)","yyyymm_bkg_sche":"202606","lst_status":"Waiting","fst_teu":2.0,"lst_teu":2.0,"norm_lst_teu":0.0,"cm1":0.0,"norm_cm1":0.0,"cm1_per_teu":0.0,"grade":"","route_profit":"","shipper_profit_tag":"","is_w3":false,"is_hi":false,"is_route_hi":false,"is_normal":false,"is_lifted":false,"is_cancel":false},{"bkg_no":"CN06813367","shipper_no":"","shipper_name":"","pol":"","pod_country":"","pod":"","dly_country":"AE","dly_plc":"KLF","vsl":"","voy":"","lst_vsl":"JESN","lst_voy":"026B8W","lst_route":"AIMT","booking_date":"2026년 6월 27일","booking_schedule":"2026년 6월 27일","cancel_date":"","week_start_date":"2026년 06월 21일","lead_time_bkg_sche":"Week of Sailing (WOS)","yyyymm_bkg_sche":"202606","lst_status":"Waiting","fst_teu":2.0,"lst_teu":2.0,"norm_lst_teu":0.0,"cm1":0.0,"norm_cm1":0.0,"cm1_per_teu":0.0,"grade":"","route_profit":"","shipper_profit_tag":"","is_w3":false,"is_hi":false,"is_route_hi":false,"is_normal":false,"is_lifted":false,"is_cancel":false},{"bkg_no":"CN06813374","shipper_no":"","shipper_name":"","pol":"","pod_country":"","pod":"","dly_country":"AE","dly_plc":"KLF","vsl":"","voy":"","lst_vsl":"JESN","lst_voy":"026B8W","lst_route":"AIMT","booking_date":"2026년 6월 27일","booking_schedule":"2026년 6월 27일","cancel_date":"","week_start_date":"2026년 06월 21일","lead_time_bkg_sche":"Week of Sailing (WOS)","yyyymm_bkg_sche":"202606","lst_status":"Waiting","fst_teu":2.0,"lst_teu":2.0,"norm_lst_teu":0.0,"cm1":0.0,"norm_cm1":0.0,"cm1_per_teu":0.0,"grade":"","route_profit":"","shipper_profit_tag":"","is_w3":false,"is_hi":false,"is_route_hi":false,"is_normal":false,"is_lifted":false,"is_cancel":false},{"bkg_no":"CN06813377","shipper_no":"","shipper_name":"","pol":"","pod_country":"","pod":"","dly_country":"AE","dly_plc":"KLF","vsl":"","voy":"","lst_vsl":"JEWS","lst_voy":"026B7W","lst_route":"AIMT","booking_date":"2026년 7월 1일","booking_schedule":"2026년 7월 1일","cancel_date":"","week_start_date":"2026년 06월 28일","lead_time_bkg_sche":"Week of Sailing (WOS)","yyyymm_bkg_sche":"202606","lst_status":"Waiting","fst_teu":2.0,"lst_teu":2.0,"norm_lst_teu":0.0,"cm1":0.0,"norm_cm1":0.0,"cm1_per_teu":0.0,"grade":"","route_profit":"","shipper_profit_tag":"","is_w3":false,"is_hi":false,"is_route_hi":false,"is_normal":false,"is_lifted":false,"is_cancel":false},{"bkg_no":"CN06813384","shipper_no":"","shipper_name":"","pol":"","pod_country":"","pod":"","dly_country":"AE","dly_plc":"KLF","vsl":"","voy":"","lst_vsl":"JEWS","lst_voy":"026B7W","lst_route":"AIMT","booking_date":"2026년 7월 1일","booking_schedule":"2026년 7월 1일","cancel_date":"","week_start_date":"2026년 06월 28일","lead_time_bkg_sche":"Week of Sailing (WOS)","yyyymm_bkg_sche":"202606","lst_status":"Waiting","fst_teu":2.0,"lst_teu":2.0,"norm_lst_teu":0.0,"cm1":0.0,"norm_cm1":0.0,"cm1_per_teu":0.0,"grade":"","route_profit":"","shipper_profit_tag":"","is_w3":false,"is_hi":false,"is_route_hi":false,"is_normal":false,"is_lifted":false,"is_cancel":false},{"bkg_no":"CN06813388","shipper_no":"","shipper_name":"","pol":"","pod_country":"","pod":"","dly_country":"AE","dly_plc":"KLF","vsl":"","voy":"","lst_vsl":"JEWS","lst_voy":"026B7W","lst_route":"AIMT","booking_date":"2026년 7월 1일","booking_schedule":"2026년 7월 1일","cancel_date":"","week_start_date":"2026년 06월 28일","lead_time_bkg_sche":"Week of Sailing (WOS)","yyyymm_bkg_sche":"202606","lst_status":"Waiting","fst_teu":2.0,"lst_teu":2.0,"norm_lst_teu":0.0,"cm1":0.0,"norm_cm1":0.0,"cm1_per_teu":0.0,"grade":"","route_profit":"","shipper_profit_tag":"","is_w3":false,"is_hi":false,"is_route_hi":false,"is_normal":false,"is_lifted":false,"is_cancel":false},{"bkg_no":"CN06813392","shipper_no":"","shipper_name":"","pol":"","pod_country":"","pod":"","dly_country":"AE","dly_plc":"KLF","vsl":"","voy":"","lst_vsl":"JEWS","lst_voy":"026B7W","lst_route":"AIMT","booking_date":"2026년 7월 1일","booking_schedule":"2026년 7월 1일","cancel_date":"","week_start_date":"2026년 06월 28일","lead_time_bkg_sche":"Week of Sailing (WOS)","yyyymm_bkg_sche":"202606","lst_status":"Waiting","fst_teu":2.0,"lst_teu":2.0,"norm_lst_teu":0.0,"cm1":0.0,"norm_cm1":0.0,"cm1_per_teu":0.0,"grade":"","route_profit":"","shipper_profit_tag":"","is_w3":false,"is_hi":false,"is_route_hi":false,"is_normal":false,"is_lifted":false,"is_cancel":false},{"bkg_no":"CN06813396","shipper_no":"","shipper_name":"","pol":"","pod_country":"","pod":"","dly_country":"AE","dly_plc":"KLF","vsl":"","voy":"","lst_vsl":"JEWS","lst_voy":"026B7W","lst_route":"AIMT","booking_date":"2026년 7월 1일","booking_schedule":"2026년 7월 1일","cancel_date":"","week_start_date":"2026년 06월 28일","lead_time_bkg_sche":"Week of Sailing (WOS)","yyyymm_bkg_sche":"202606","lst_status":"Waiting","fst_teu":2.0,"lst_teu":2.0,"norm_lst_teu":0.0,"cm1":0.0,"norm_cm1":0.0,"cm1_per_teu":0.0,"grade":"","route_profit":"","shipper_profit_tag":"","is_w3":false,"is_hi":false,"is_route_hi":false,"is_normal":false,"is_lifted":false,"is_cancel":false},{"bkg_no":"CN06813441","shipper_no":"","shipper_name":"","pol":"","pod_country":"","pod":"","dly_country":"MY","dly_plc":"PGU","vsl":"","voy":"","lst_vsl":"FDR","lst_voy":"260605","lst_route":"AIS","booking_date":"2026년 6월 5일","booking_schedule":"2026년 6월 5일","cancel_date":"","week_start_date":"2026년 05월 31일","lead_time_bkg_sche":"Week of Sailing (WOS)","yyyymm_bkg_sche":"202606","lst_status":"Waiting","fst_teu":5.0,"lst_teu":5.0,"norm_lst_teu":0.0,"cm1":2300.0,"norm_cm1":0.0,"cm1_per_teu":460.0,"grade":"","route_profit":"고수익","shipper_profit_tag":"","is_w3":false,"is_hi":true,"is_route_hi":true,"is_normal":false,"is_lifted":false,"is_cancel":false},{"bkg_no":"CN06813444","shipper_no":"","shipper_name":"","pol":"","pod_country":"","pod":"","dly_country":"MY","dly_plc":"PGU","vsl":"","voy":"","lst_vsl":"FDR","lst_voy":"260605","lst_route":"AIS","booking_date":"2026년 6월 5일","booking_schedule":"2026년 6월 5일","cancel_date":"","week_start_date":"2026년 05월 31일","lead_time_bkg_sche":"Week of Sailing (WOS)","yyyymm_bkg_sche":"202606","lst_status":"Waiting","fst_teu":5.0,"lst_teu":5.0,"norm_lst_teu":0.0,"cm1":2300.0,"norm_cm1":0.0,"cm1_per_teu":460.0,"grade":"","route_profit":"고수익","shipper_profit_tag":"","is_w3":false,"is_hi":true,"is_route_hi":true,"is_normal":false,"is_lifted":false,"is_cancel":false},{"bkg_no":"CN06813449","shipper_no":"","shipper_name":"","pol":"","pod_country":"","pod":"","dly_country":"MY","dly_plc":"PEN","vsl":"","voy":"","lst_vsl":"FDR","lst_voy":"260601","lst_route":"KCM","booking_date":"2026년 6월 1일","booking_schedule":"2026년 6월 1일","cancel_date":"","week_start_date":"2026년 05월 31일","lead_time_bkg_sche":"Week of Sailing (WOS)","yyyymm_bkg_sche":"202606","lst_status":"Waiting","fst_teu":10.0,"lst_teu":10.0,"norm_lst_teu":0.0,"cm1":3610.0,"norm_cm1":0.0,"cm1_per_teu":361.0,"grade":"","route_profit":"고수익","shipper_profit_tag":"","is_w3":false,"is_hi":true,"is_route_hi":true,"is_normal":false,"is_lifted":false,"is_cancel":false},{"bkg_no":"CN06813450","shipper_no":"","shipper_name":"","pol":"","pod_country":"","pod":"","dly_country":"MY","dly_plc":"PEN","vsl":"","voy":"","lst_vsl":"FDR","lst_voy":"260608","lst_route":"KCM","booking_date":"2026년 6월 8일","booking_schedule":"2026년 6월 8일","cancel_date":"","week_start_date":"2026년 06월 07일","lead_time_bkg_sche":"Week of Sailing (WOS)","yyyymm_bkg_sche":"202606","lst_status":"Normal","fst_teu":10.0,"lst_teu":10.0,"norm_lst_teu":10.0,"cm1":3610.0,"norm_cm1":3610.0,"cm1_per_teu":361.0,"grade":"","route_profit":"고수익","shipper_profit_tag":"","is_w3":false,"is_hi":true,"is_route_hi":true,"is_normal":true,"is_lifted":true,"is_cancel":false},{"bkg_no":"CN06817727","shipper_no":"","shipper_name":"","pol":"","pod_country":"","pod":"","dly_country":"AE","dly_plc":"KLF","vsl":"","voy":"","lst_vsl":"JESN","lst_voy":"026B8W","lst_route":"AIMT","booking_date":"2026년 6월 27일","booking_schedule":"2026년 6월 27일","cancel_date":"","week_start_date":"2026년 06월 21일","lead_time_bkg_sche":"Week of Sailing (WOS)","yyyymm_bkg_sche":"202606","lst_status":"Waiting","fst_teu":2.0,"lst_teu":2.0,"norm_lst_teu":0.0,"cm1":4628.0,"norm_cm1":0.0,"cm1_per_teu":2314.0,"grade":"","route_profit":"","shipper_profit_tag":"","is_w3":false,"is_hi":false,"is_route_hi":false,"is_normal":false,"is_lifted":false,"is_cancel":false},{"bkg_no":"CN06817729","shipper_no":"","shipper_name":"","pol":"","pod_country":"","pod":"","dly_country":"AE","dly_plc":"KLF","vsl":"","voy":"","lst_vsl":"JESN","lst_voy":"026B8W","lst_route":"AIMT","booking_date":"2026년 6월 27일","booking_schedule":"2026년 6월 27일","cancel_date":"","week_start_date":"2026년 06월 21일","lead_time_bkg_sche":"Week of Sailing (WOS)","yyyymm_bkg_sche":"202606","lst_status":"Waiting","fst_teu":2.0,"lst_teu":2.0,"norm_lst_teu":0.0,"cm1":4628.0,"norm_cm1":0.0,"cm1_per_teu":2314.0,"grade":"","route_profit":"","shipper_profit_tag":"","is_w3":false,"is_hi":false,"is_route_hi":false,"is_normal":false,"is_lifted":false,"is_cancel":false},{"bkg_no":"CN06818073","shipper_no":"","shipper_name":"","pol":"","pod_country":"","pod":"","dly_country":"AE","dly_plc":"KLF","vsl":"","voy":"","lst_vsl":"JESN","lst_voy":"026B8W","lst_route":"AIMT","booking_date":"2026년 6월 27일","booking_schedule":"2026년 6월 27일","cancel_date":"","week_start_date":"2026년 06월 21일","lead_time_bkg_sche":"Week of Sailing (WOS)","yyyymm_bkg_sche":"202606","lst_status":"Waiting","fst_teu":2.0,"lst_teu":2.0,"norm_lst_teu":0.0,"cm1":4628.0,"norm_cm1":0.0,"cm1_per_teu":2314.0,"grade":"","route_profit":"","shipper_profit_tag":"","is_w3":false,"is_hi":false,"is_route_hi":false,"is_normal":false,"is_lifted":false,"is_cancel":false},{"bkg_no":"CN06818092","shipper_no":"","shipper_name":"","pol":"","pod_country":"","pod":"","dly_country":"AE","dly_plc":"KLF","vsl":"","voy":"","lst_vsl":"JESN","lst_voy":"026B8W","lst_route":"AIMT","booking_date":"2026년 6월 27일","booking_schedule":"2026년 6월 27일","cancel_date":"","week_start_date":"2026년 06월 21일","lead_time_bkg_sche":"Week of Sailing (WOS)","yyyymm_bkg_sche":"202606","lst_status":"Waiting","fst_teu":2.0,"lst_teu":2.0,"norm_lst_teu":0.0,"cm1":4628.0,"norm_cm1":0.0,"cm1_per_teu":2314.0,"grade":"","route_profit":"","shipper_profit_tag":"","is_w3":false,"is_hi":false,"is_route_hi":false,"is_normal":false,"is_lifted":false,"is_cancel":false},{"bkg_no":"CN06820775","shipper_no":"","shipper_name":"","pol":"","pod_country":"","pod":"","dly_country":"AE","dly_plc":"KLF","vsl":"","voy":"","lst_vsl":"JESN","lst_voy":"026B8W","lst_route":"AIMT","booking_date":"2026년 6월 27일","booking_schedule":"2026년 6월 27일","cancel_date":"","week_start_date":"2026년 06월 21일","lead_time_bkg_sche":"Week of Sailing (WOS)","yyyymm_bkg_sche":"202606","lst_status":"Waiting","fst_teu":2.0,"lst_teu":2.0,"norm_lst_teu":0.0,"cm1":4198.0,"norm_cm1":0.0,"cm1_per_teu":2099.0,"grade":"","route_profit":"","shipper_profit_tag":"","is_w3":false,"is_hi":false,"is_route_hi":false,"is_normal":false,"is_lifted":false,"is_cancel":false},{"bkg_no":"CN06820780","shipper_no":"","shipper_name":"","pol":"","pod_country":"","pod":"","dly_country":"AE","dly_plc":"KLF","vsl":"","voy":"","lst_vsl":"JESN","lst_voy":"026B8W","lst_route":"AIMT","booking_date":"2026년 6월 27일","booking_schedule":"2026년 6월 27일","cancel_date":"","week_start_date":"2026년 06월 21일","lead_time_bkg_sche":"Week of Sailing (WOS)","yyyymm_bkg_sche":"202606","lst_status":"Waiting","fst_teu":2.0,"lst_teu":2.0,"norm_lst_teu":0.0,"cm1":4198.0,"norm_cm1":0.0,"cm1_per_teu":2099.0,"grade":"","route_profit":"","shipper_profit_tag":"","is_w3":false,"is_hi":false,"is_route_hi":false,"is_normal":false,"is_lifted":false,"is_cancel":false},{"bkg_no":"CN06820790","shipper_no":"","shipper_name":"","pol":"","pod_country":"","pod":"","dly_country":"AE","dly_plc":"KLF","vsl":"","voy":"","lst_vsl":"JESN","lst_voy":"026B8W","lst_route":"AIMT","booking_date":"2026년 6월 27일","booking_schedule":"2026년 6월 27일","cancel_date":"","week_start_date":"2026년 06월 21일","lead_time_bkg_sche":"Week of Sailing (WOS)","yyyymm_bkg_sche":"202606","lst_status":"Waiting","fst_teu":2.0,"lst_teu":2.0,"norm_lst_teu":0.0,"cm1":4198.0,"norm_cm1":0.0,"cm1_per_teu":2099.0,"grade":"","route_profit":"","shipper_profit_tag":"","is_w3":false,"is_hi":false,"is_route_hi":false,"is_normal":false,"is_lifted":false,"is_cancel":false},{"bkg_no":"CN06820799","shipper_no":"","shipper_name":"","pol":"","pod_country":"","pod":"","dly_country":"AE","dly_plc":"KLF","vsl":"","voy":"","lst_vsl":"JEWS","lst_voy":"026B7W","lst_route":"AIMT","booking_date":"2026년 7월 4일","booking_schedule":"2026년 7월 4일","cancel_date":"","week_start_date":"2026년 06월 28일","lead_time_bkg_sche":"Week of Sailing (WOS)","yyyymm_bkg_sche":"202606","lst_status":"Waiting","fst_teu":2.0,"lst_teu":2.0,"norm_lst_teu":0.0,"cm1":4198.0,"norm_cm1":0.0,"cm1_per_teu":2099.0,"grade":"","route_profit":"","shipper_profit_tag":"","is_w3":false,"is_hi":false,"is_route_hi":false,"is_normal":false,"is_lifted":false,"is_cancel":false},{"bkg_no":"CN06820803","shipper_no":"","shipper_name":"","pol":"","pod_country":"","pod":"","dly_country":"AE","dly_plc":"KLF","vsl":"","voy":"","lst_vsl":"JEWS","lst_voy":"026B7W","lst_route":"AIMT","booking_date":"2026년 7월 4일","booking_schedule":"2026년 7월 4일","cancel_date":"","week_start_date":"2026년 06월 28일","lead_time_bkg_sche":"Week of Sailing (WOS)","yyyymm_bkg_sche":"202606","lst_status":"Waiting","fst_teu":2.0,"lst_teu":2.0,"norm_lst_teu":0.0,"cm1":4198.0,"norm_cm1":0.0,"cm1_per_teu":2099.0,"grade":"","route_profit":"","shipper_profit_tag":"","is_w3":false,"is_hi":false,"is_route_hi":false,"is_normal":false,"is_lifted":false,"is_cancel":false},{"bkg_no":"CN06820806","shipper_no":"","shipper_name":"","pol":"","pod_country":"","pod":"","dly_country":"AE","dly_plc":"KLF","vsl":"","voy":"","lst_vsl":"JEWS","lst_voy":"026B7W","lst_route":"AIMT","booking_date":"2026년 7월 4일","booking_schedule":"2026년 7월 4일","cancel_date":"","week_start_date":"2026년 06월 28일","lead_time_bkg_sche":"Week of Sailing (WOS)","yyyymm_bkg_sche":"202606","lst_status":"Waiting","fst_teu":2.0,"lst_teu":2.0,"norm_lst_teu":0.0,"cm1":4198.0,"norm_cm1":0.0,"cm1_per_teu":2099.0,"grade":"","route_profit":"","shipper_profit_tag":"","is_w3":false,"is_hi":false,"is_route_hi":false,"is_normal":false,"is_lifted":false,"is_cancel":false},{"bkg_no":"CN06820908","shipper_no":"","shipper_name":"","pol":"","pod_country":"","pod":"","dly_country":"AE","dly_plc":"KLF","vsl":"","voy":"","lst_vsl":"JESN","lst_voy":"026B8W","lst_route":"AIMT","booking_date":"2026년 6월 27일","booking_schedule":"2026년 6월 27일","cancel_date":"","week_start_date":"2026년 06월 21일","lead_time_bkg_sche":"Week of Sailing (WOS)","yyyymm_bkg_sche":"202606","lst_status":"Waiting","fst_teu":2.0,"lst_teu":2.0,"norm_lst_teu":0.0,"cm1":4198.0,"norm_cm1":0.0,"cm1_per_teu":2099.0,"grade":"","route_profit":"","shipper_profit_tag":"","is_w3":false,"is_hi":false,"is_route_hi":false,"is_normal":false,"is_lifted":false,"is_cancel":false},{"bkg_no":"CN06820914","shipper_no":"","shipper_name":"","pol":"","pod_country":"","pod":"","dly_country":"AE","dly_plc":"KLF","vsl":"","voy":"","lst_vsl":"JESN","lst_voy":"026B8W","lst_route":"AIMT","booking_date":"2026년 6월 27일","booking_schedule":"2026년 6월 27일","cancel_date":"","week_start_date":"2026년 06월 21일","lead_time_bkg_sche":"Week of Sailing (WOS)","yyyymm_bkg_sche":"202606","lst_status":"Waiting","fst_teu":2.0,"lst_teu":2.0,"norm_lst_teu":0.0,"cm1":4198.0,"norm_cm1":0.0,"cm1_per_teu":2099.0,"grade":"","route_profit":"","shipper_profit_tag":"","is_w3":false,"is_hi":false,"is_route_hi":false,"is_normal":false,"is_lifted":false,"is_cancel":false},{"bkg_no":"CN06820918","shipper_no":"","shipper_name":"","pol":"","pod_country":"","pod":"","dly_country":"AE","dly_plc":"KLF","vsl":"","voy":"","lst_vsl":"JESN","lst_voy":"026B8W","lst_route":"AIMT","booking_date":"2026년 6월 27일","booking_schedule":"2026년 6월 27일","cancel_date":"","week_start_date":"2026년 06월 21일","lead_time_bkg_sche":"Week of Sailing (WOS)","yyyymm_bkg_sche":"202606","lst_status":"Waiting","fst_teu":2.0,"lst_teu":2.0,"norm_lst_teu":0.0,"cm1":4198.0,"norm_cm1":0.0,"cm1_per_teu":2099.0,"grade":"","route_profit":"","shipper_profit_tag":"","is_w3":false,"is_hi":false,"is_route_hi":false,"is_normal":false,"is_lifted":false,"is_cancel":false},{"bkg_no":"CN06820980","shipper_no":"","shipper_name":"","pol":"","pod_country":"","pod":"","dly_country":"AE","dly_plc":"KLF","vsl":"","voy":"","lst_vsl":"JESN","lst_voy":"026B8W","lst_route":"AIMT","booking_date":"2026년 6월 27일","booking_schedule":"2026년 6월 27일","cancel_date":"","week_start_date":"2026년 06월 21일","lead_time_bkg_sche":"Week of Sailing (WOS)","yyyymm_bkg_sche":"202606","lst_status":"Waiting","fst_teu":2.0,"lst_teu":2.0,"norm_lst_teu":0.0,"cm1":4198.0,"norm_cm1":0.0,"cm1_per_teu":2099.0,"grade":"","route_profit":"","shipper_profit_tag":"","is_w3":false,"is_hi":false,"is_route_hi":false,"is_normal":false,"is_lifted":false,"is_cancel":false},{"bkg_no":"CN06821004","shipper_no":"","shipper_name":"","pol":"","pod_country":"","pod":"","dly_country":"AE","dly_plc":"KLF","vsl":"","voy":"","lst_vsl":"JESN","lst_voy":"026B8W","lst_route":"AIMT","booking_date":"2026년 6월 27일","booking_schedule":"2026년 6월 27일","cancel_date":"","week_start_date":"2026년 06월 21일","lead_time_bkg_sche":"Week of Sailing (WOS)","yyyymm_bkg_sche":"202606","lst_status":"Waiting","fst_teu":2.0,"lst_teu":2.0,"norm_lst_teu":0.0,"cm1":4198.0,"norm_cm1":0.0,"cm1_per_teu":2099.0,"grade":"","route_profit":"","shipper_profit_tag":"","is_w3":false,"is_hi":false,"is_route_hi":false,"is_normal":false,"is_lifted":false,"is_cancel":false},{"bkg_no":"CN06821007","shipper_no":"","shipper_name":"","pol":"","pod_country":"","pod":"","dly_country":"OM","dly_plc":"SOH","vsl":"","voy":"","lst_vsl":"JESN","lst_voy":"026B8W","lst_route":"AIMT","booking_date":"2026년 6월 27일","booking_schedule":"2026년 6월 27일","cancel_date":"","week_start_date":"2026년 06월 21일","lead_time_bkg_sche":"Week of Sailing (WOS)","yyyymm_bkg_sche":"202606","lst_status":"Waiting","fst_teu":2.0,"lst_teu":2.0,"norm_lst_teu":0.0,"cm1":5110.0,"norm_cm1":0.0,"cm1_per_teu":2555.0,"grade":"","route_profit":"","shipper_profit_tag":"","is_w3":false,"is_hi":false,"is_route_hi":false,"is_normal":false,"is_lifted":false,"is_cancel":false},{"bkg_no":"CN06821011","shipper_no":"","shipper_name":"","pol":"","pod_country":"","pod":"","dly_country":"OM","dly_plc":"SOH","vsl":"","voy":"","lst_vsl":"JESN","lst_voy":"026B8W","lst_route":"AIMT","booking_date":"2026년 6월 27일","booking_schedule":"2026년 6월 27일","cancel_date":"","week_start_date":"2026년 06월 21일","lead_time_bkg_sche":"Week of Sailing (WOS)","yyyymm_bkg_sche":"202606","lst_status":"Waiting","fst_teu":2.0,"lst_teu":2.0,"norm_lst_teu":0.0,"cm1":5110.0,"norm_cm1":0.0,"cm1_per_teu":2555.0,"grade":"","route_profit":"","shipper_profit_tag":"","is_w3":false,"is_hi":false,"is_route_hi":false,"is_normal":false,"is_lifted":false,"is_cancel":false},{"bkg_no":"CN06822398","shipper_no":"","shipper_name":"","pol":"","pod_country":"","pod":"","dly_country":"MY","dly_plc":"PGU","vsl":"","voy":"","lst_vsl":"FDR","lst_voy":"260619","lst_route":"AIS3","booking_date":"2026년 6월 19일","booking_schedule":"2026년 6월 19일","cancel_date":"","week_start_date":"2026년 06월 14일","lead_time_bkg_sche":"Week of Sailing (WOS)","yyyymm_bkg_sche":"202606","lst_status":"Waiting","fst_teu":2.0,"lst_teu":2.0,"norm_lst_teu":0.0,"cm1":0.0,"norm_cm1":0.0,"cm1_per_teu":0.0,"grade":"","route_profit":"고수익","shipper_profit_tag":"","is_w3":false,"is_hi":true,"is_route_hi":true,"is_normal":false,"is_lifted":false,"is_cancel":false},{"bkg_no":"CN06823635","shipper_no":"","shipper_name":"","pol":"","pod_country":"","pod":"","dly_country":"MY","dly_plc":"PGU","vsl":"","voy":"","lst_vsl":"FDR","lst_voy":"260605","lst_route":"AIS","booking_date":"2026년 6월 5일","booking_schedule":"2026년 6월 5일","cancel_date":"","week_start_date":"2026년 05월 31일","lead_time_bkg_sche":"Week of Sailing (WOS)","yyyymm_bkg_sche":"202606","lst_status":"Cancel","fst_teu":5.0,"lst_teu":5.0,"norm_lst_teu":0.0,"cm1":0.0,"norm_cm1":0.0,"cm1_per_teu":0.0,"grade":"","route_profit":"고수익","shipper_profit_tag":"","is_w3":false,"is_hi":true,"is_route_hi":true,"is_normal":false,"is_lifted":false,"is_cancel":true},{"bkg_no":"CN06823708","shipper_no":"","shipper_name":"","pol":"","pod_country":"","pod":"","dly_country":"MY","dly_plc":"PGU","vsl":"","voy":"","lst_vsl":"FDR","lst_voy":"260605","lst_route":"AIS","booking_date":"2026년 6월 5일","booking_schedule":"2026년 6월 5일","cancel_date":"","week_start_date":"2026년 05월 31일","lead_time_bkg_sche":"Week of Sailing (WOS)","yyyymm_bkg_sche":"202606","lst_status":"Cancel","fst_teu":5.0,"lst_teu":5.0,"norm_lst_teu":0.0,"cm1":0.0,"norm_cm1":0.0,"cm1_per_teu":0.0,"grade":"","route_profit":"고수익","shipper_profit_tag":"","is_w3":false,"is_hi":true,"is_route_hi":true,"is_normal":false,"is_lifted":false,"is_cancel":true},{"bkg_no":"CN06825049","shipper_no":"","shipper_name":"","pol":"","pod_country":"","pod":"","dly_country":"MY","dly_plc":"PGU","vsl":"","voy":"","lst_vsl":"FDR","lst_voy":"260628","lst_route":"KCM","booking_date":"2026년 6월 28일","booking_schedule":"2026년 6월 28일","cancel_date":"","week_start_date":"2026년 06월 28일","lead_time_bkg_sche":"Week of Sailing (WOS)","yyyymm_bkg_sche":"202606","lst_status":"Normal","fst_teu":5.0,"lst_teu":5.0,"norm_lst_teu":5.0,"cm1":2310.0,"norm_cm1":2310.0,"cm1_per_teu":462.0,"grade":"","route_profit":"고수익","shipper_profit_tag":"","is_w3":false,"is_hi":true,"is_route_hi":true,"is_normal":true,"is_lifted":true,"is_cancel":false},{"bkg_no":"CN06825054","shipper_no":"","shipper_name":"","pol":"","pod_country":"","pod":"","dly_country":"MY","dly_plc":"PGU","vsl":"","voy":"","lst_vsl":"FDR","lst_voy":"260628","lst_route":"KCM","booking_date":"2026년 6월 28일","booking_schedule":"2026년 6월 28일","cancel_date":"","week_start_date":"2026년 06월 28일","lead_time_bkg_sche":"Week of Sailing (WOS)","yyyymm_bkg_sche":"202606","lst_status":"Normal","fst_teu":5.0,"lst_teu":5.0,"norm_lst_teu":5.0,"cm1":2310.0,"norm_cm1":2310.0,"cm1_per_teu":462.0,"grade":"","route_profit":"고수익","shipper_profit_tag":"","is_w3":false,"is_hi":true,"is_route_hi":true,"is_normal":true,"is_lifted":true,"is_cancel":false},{"bkg_no":"CN06825076","shipper_no":"","shipper_name":"","pol":"","pod_country":"","pod":"","dly_country":"TZ","dly_plc":"DAR","vsl":"","voy":"","lst_vsl":"JEMB","lst_voy":"02626W","lst_route":"EAX","booking_date":"2026년 6월 28일","booking_schedule":"2026년 6월 28일","cancel_date":"","week_start_date":"2026년 06월 28일","lead_time_bkg_sche":"Week of Sailing (WOS)","yyyymm_bkg_sche":"202606","lst_status":"Waiting","fst_teu":2.0,"lst_teu":2.0,"norm_lst_teu":0.0,"cm1":2118.0,"norm_cm1":0.0,"cm1_per_teu":1059.0,"grade":"","route_profit":"","shipper_profit_tag":"","is_w3":false,"is_hi":false,"is_route_hi":false,"is_normal":false,"is_lifted":false,"is_cancel":false},{"bkg_no":"CN06825087","shipper_no":"","shipper_name":"","pol":"","pod_country":"","pod":"","dly_country":"TZ","dly_plc":"DAR","vsl":"","voy":"","lst_vsl":"JEMB","lst_voy":"02626W","lst_route":"EAX","booking_date":"2026년 6월 28일","booking_schedule":"2026년 6월 28일","cancel_date":"","week_start_date":"2026년 06월 28일","lead_time_bkg_sche":"Week of Sailing (WOS)","yyyymm_bkg_sche":"202606","lst_status":"Waiting","fst_teu":2.0,"lst_teu":2.0,"norm_lst_teu":0.0,"cm1":2118.0,"norm_cm1":0.0,"cm1_per_teu":1059.0,"grade":"","route_profit":"","shipper_profit_tag":"","is_w3":false,"is_hi":false,"is_route_hi":false,"is_normal":false,"is_lifted":false,"is_cancel":false},{"bkg_no":"CN06825938","shipper_no":"","shipper_name":"","pol":"","pod_country":"","pod":"","dly_country":"ID","dly_plc":"SRG","vsl":"","voy":"","lst_vsl":"JNGS","lst_voy":"0052S","lst_route":"KCS2","booking_date":"2026년 7월 1일","booking_schedule":"2026년 7월 1일","cancel_date":"","week_start_date":"2026년 06월 28일","lead_time_bkg_sche":"Week of Sailing (WOS)","yyyymm_bkg_sche":"202606","lst_status":"Normal","fst_teu":6.0,"lst_teu":6.0,"norm_lst_teu":6.0,"cm1":3054.0,"norm_cm1":3054.0,"cm1_per_teu":509.0,"grade":"","route_profit":"고수익","shipper_profit_tag":"","is_w3":false,"is_hi":true,"is_route_hi":true,"is_normal":true,"is_lifted":true,"is_cancel":false},{"bkg_no":"CN06825953","shipper_no":"","shipper_name":"","pol":"","pod_country":"","pod":"","dly_country":"VN","dly_plc":"SGN","vsl":"","voy":"","lst_vsl":"FDR","lst_voy":"260605","lst_route":"KVT","booking_date":"2026년 6월 5일","booking_schedule":"2026년 6월 5일","cancel_date":"","week_start_date":"2026년 05월 31일","lead_time_bkg_sche":"Week of Sailing (WOS)","yyyymm_bkg_sche":"202606","lst_status":"Normal","fst_teu":8.0,"lst_teu":8.0,"norm_lst_teu":8.0,"cm1":3320.0,"norm_cm1":3320.0,"cm1_per_teu":415.0,"grade":"","route_profit":"고수익","shipper_profit_tag":"","is_w3":false,"is_hi":true,"is_route_hi":true,"is_normal":true,"is_lifted":true,"is_cancel":false},{"bkg_no":"CN06825955","shipper_no":"","shipper_name":"","pol":"","pod_country":"","pod":"","dly_country":"VN","dly_plc":"SGN","vsl":"","voy":"","lst_vsl":"FDR","lst_voy":"260611","lst_route":"VTS","booking_date":"2026년 6월 11일","booking_schedule":"2026년 6월 11일","cancel_date":"","week_start_date":"2026년 06월 07일","lead_time_bkg_sche":"Week of Sailing (WOS)","yyyymm_bkg_sche":"202606","lst_status":"Normal","fst_teu":10.0,"lst_teu":10.0,"norm_lst_teu":10.0,"cm1":4150.0,"norm_cm1":4150.0,"cm1_per_teu":415.0,"grade":"","route_profit":"고수익","shipper_profit_tag":"","is_w3":false,"is_hi":true,"is_route_hi":true,"is_normal":true,"is_lifted":true,"is_cancel":false},{"bkg_no":"CN06826989","shipper_no":"","shipper_name":"","pol":"","pod_country":"","pod":"","dly_country":"TH","dly_plc":"LCH","vsl":"","voy":"","lst_vsl":"JLBM","lst_voy":"054S","lst_route":"RBH","booking_date":"2026년 6월 26일","booking_schedule":"2026년 6월 26일","cancel_date":"","week_start_date":"2026년 06월 21일","lead_time_bkg_sche":"Week of Sailing (WOS)","yyyymm_bkg_sche":"202606","lst_status":"Waiting","fst_teu":2.0,"lst_teu":2.0,"norm_lst_teu":0.0,"cm1":640.0,"norm_cm1":0.0,"cm1_per_teu":320.0,"grade":"","route_profit":"","shipper_profit_tag":"","is_w3":false,"is_hi":false,"is_route_hi":false,"is_normal":false,"is_lifted":false,"is_cancel":false},{"bkg_no":"CN06826993","shipper_no":"","shipper_name":"","pol":"","pod_country":"","pod":"","dly_country":"TH","dly_plc":"LCH","vsl":"","voy":"","lst_vsl":"JLBM","lst_voy":"054S","lst_route":"RBH","booking_date":"2026년 6월 26일","booking_schedule":"2026년 6월 26일","cancel_date":"","week_start_date":"2026년 06월 21일","lead_time_bkg_sche":"Week of Sailing (WOS)","yyyymm_bkg_sche":"202606","lst_status":"Waiting","fst_teu":2.0,"lst_teu":2.0,"norm_lst_teu":0.0,"cm1":640.0,"norm_cm1":0.0,"cm1_per_teu":320.0,"grade":"","route_profit":"","shipper_profit_tag":"","is_w3":false,"is_hi":false,"is_route_hi":false,"is_normal":false,"is_lifted":false,"is_cancel":false},{"bkg_no":"CN06827001","shipper_no":"","shipper_name":"","pol":"","pod_country":"","pod":"","dly_country":"TH","dly_plc":"LCH","vsl":"","voy":"","lst_vsl":"JLBM","lst_voy":"054S","lst_route":"RBH","booking_date":"2026년 6월 26일","booking_schedule":"2026년 6월 26일","cancel_date":"","week_start_date":"2026년 06월 21일","lead_time_bkg_sche":"Week of Sailing (WOS)","yyyymm_bkg_sche":"202606","lst_status":"Waiting","fst_teu":2.0,"lst_teu":2.0,"norm_lst_teu":0.0,"cm1":640.0,"norm_cm1":0.0,"cm1_per_teu":320.0,"grade":"","route_profit":"","shipper_profit_tag":"","is_w3":false,"is_hi":false,"is_route_hi":false,"is_normal":false,"is_lifted":false,"is_cancel":false},{"bkg_no":"CN06827053","shipper_no":"","shipper_name":"","pol":"","pod_country":"","pod":"","dly_country":"ID","dly_plc":"JKT","vsl":"","voy":"","lst_vsl":"JNGS","lst_voy":"0052S","lst_route":"KCS2","booking_date":"2026년 7월 1일","booking_schedule":"2026년 7월 1일","cancel_date":"","week_start_date":"2026년 06월 28일","lead_time_bkg_sche":"Week of Sailing (WOS)","yyyymm_bkg_sche":"202606","lst_status":"Waiting","fst_teu":2.0,"lst_teu":2.0,"norm_lst_teu":0.0,"cm1":1024.0,"norm_cm1":0.0,"cm1_per_teu":512.0,"grade":"","route_profit":"고수익","shipper_profit_tag":"","is_w3":false,"is_hi":true,"is_route_hi":true,"is_normal":false,"is_lifted":false,"is_cancel":false},{"bkg_no":"CN06827061","shipper_no":"","shipper_name":"","pol":"","pod_country":"","pod":"","dly_country":"ID","dly_plc":"JKT","vsl":"","voy":"","lst_vsl":"JNGS","lst_voy":"0052S","lst_route":"KCS2","booking_date":"2026년 7월 1일","booking_schedule":"2026년 7월 1일","cancel_date":"","week_start_date":"2026년 06월 28일","lead_time_bkg_sche":"Week of Sailing (WOS)","yyyymm_bkg_sche":"202606","lst_status":"Waiting","fst_teu":2.0,"lst_teu":2.0,"norm_lst_teu":0.0,"cm1":1024.0,"norm_cm1":0.0,"cm1_per_teu":512.0,"grade":"","route_profit":"고수익","shipper_profit_tag":"","is_w3":false,"is_hi":true,"is_route_hi":true,"is_normal":false,"is_lifted":false,"is_cancel":false},{"bkg_no":"CN06828341","shipper_no":"SUGZ06","shipper_name":"SHENZHEN UNIEVER LOGISTICS CO.,LTD","pol":"NNS","pod_country":"AE","pod":"KLF","dly_country":"AE","dly_plc":"KLF","vsl":"JGGX","voy":"026B4W","lst_vsl":"JGGX","lst_voy":"026B4W","lst_route":"AIMT","booking_date":"2026년 5월 21일","booking_schedule":"2026년 6월 3일","cancel_date":"","week_start_date":"2026년 05월 31일","lead_time_bkg_sche":"WOS-2","yyyymm_bkg_sche":"202606","lst_status":"Normal","fst_teu":2.0,"lst_teu":2.0,"norm_lst_teu":2.0,"cm1":0.0,"norm_cm1":0.0,"cm1_per_teu":0.0,"grade":"","route_profit":"","shipper_profit_tag":"","is_w3":false,"is_hi":false,"is_route_hi":false,"is_normal":true,"is_lifted":true,"is_cancel":false},{"bkg_no":"CN06828392","shipper_no":"SUGZ06","shipper_name":"SHENZHEN UNIEVER LOGISTICS CO.,LTD","pol":"NNS","pod_country":"AE","pod":"KLF","dly_country":"AE","dly_plc":"KLF","vsl":"JGGX","voy":"026B4W","lst_vsl":"JGGX","lst_voy":"026B4W","lst_route":"AIMT","booking_date":"2026년 5월 21일","booking_schedule":"2026년 6월 3일","cancel_date":"","week_start_date":"2026년 05월 31일","lead_time_bkg_sche":"WOS-2","yyyymm_bkg_sche":"202606","lst_status":"Normal","fst_teu":2.0,"lst_teu":2.0,"norm_lst_teu":2.0,"cm1":0.0,"norm_cm1":0.0,"cm1_per_teu":0.0,"grade":"","route_profit":"","shipper_profit_tag":"","is_w3":false,"is_hi":false,"is_route_hi":false,"is_normal":true,"is_lifted":true,"is_cancel":false},{"bkg_no":"CN06828409","shipper_no":"SUGZ06","shipper_name":"SHENZHEN UNIEVER LOGISTICS CO.,LTD","pol":"NNS","pod_country":"AE","pod":"KLF","dly_country":"AE","dly_plc":"KLF","vsl":"JGGX","voy":"026B4W","lst_vsl":"JGGX","lst_voy":"026B4W","lst_route":"AIMT","booking_date":"2026년 5월 21일","booking_schedule":"2026년 6월 3일","cancel_date":"","week_start_date":"2026년 05월 31일","lead_time_bkg_sche":"WOS-2","yyyymm_bkg_sche":"202606","lst_status":"Normal","fst_teu":2.0,"lst_teu":2.0,"norm_lst_teu":2.0,"cm1":0.0,"norm_cm1":0.0,"cm1_per_teu":0.0,"grade":"","route_profit":"","shipper_profit_tag":"","is_w3":false,"is_hi":false,"is_route_hi":false,"is_normal":true,"is_lifted":true,"is_cancel":false},{"bkg_no":"CN06828412","shipper_no":"SUGZ06","shipper_name":"SHENZHEN UNIEVER LOGISTICS CO.,LTD","pol":"NNS","pod_country":"AE","pod":"KLF","dly_country":"AE","dly_plc":"KLF","vsl":"JGGX","voy":"026B4W","lst_vsl":"JGGX","lst_voy":"026B4W","lst_route":"AIMT","booking_date":"2026년 5월 21일","booking_schedule":"2026년 6월 3일","cancel_date":"","week_start_date":"2026년 05월 31일","lead_time_bkg_sche":"WOS-2","yyyymm_bkg_sche":"202606","lst_status":"Normal","fst_teu":2.0,"lst_teu":2.0,"norm_lst_teu":2.0,"cm1":0.0,"norm_cm1":0.0,"cm1_per_teu":0.0,"grade":"","route_profit":"","shipper_profit_tag":"","is_w3":false,"is_hi":false,"is_route_hi":false,"is_normal":true,"is_lifted":true,"is_cancel":false},{"bkg_no":"CN06829066","shipper_no":"","shipper_name":"","pol":"","pod_country":"","pod":"","dly_country":"MY","dly_plc":"PEN","vsl":"","voy":"","lst_vsl":"FDR","lst_voy":"260625","lst_route":"KCM","booking_date":"2026년 6월 25일","booking_schedule":"2026년 6월 25일","cancel_date":"","week_start_date":"2026년 06월 21일","lead_time_bkg_sche":"Week of Sailing (WOS)","yyyymm_bkg_sche":"202606","lst_status":"Waiting","fst_teu":10.0,"lst_teu":10.0,"norm_lst_teu":0.0,"cm1":3610.0,"norm_cm1":0.0,"cm1_per_teu":361.0,"grade":"","route_profit":"고수익","shipper_profit_tag":"","is_w3":false,"is_hi":true,"is_route_hi":true,"is_normal":false,"is_lifted":false,"is_cancel":false},{"bkg_no":"CN06829307","shipper_no":"SUGZ06","shipper_name":"SHENZHEN UNIEVER LOGISTICS CO.,LTD","pol":"NNS","pod_country":"AE","pod":"KLF","dly_country":"AE","dly_plc":"JEA","vsl":"JGGX","voy":"026B4W","lst_vsl":"JGGX","lst_voy":"026B4W","lst_route":"AIMT","booking_date":"2026년 5월 22일","booking_schedule":"2026년 6월 4일","cancel_date":"","week_start_date":"2026년 05월 31일","lead_time_bkg_sche":"WOS-2","yyyymm_bkg_sche":"202606","lst_status":"Normal","fst_teu":2.0,"lst_teu":2.0,"norm_lst_teu":2.0,"cm1":0.0,"norm_cm1":0.0,"cm1_per_teu":0.0,"grade":"","route_profit":"","shipper_profit_tag":"","is_w3":false,"is_hi":false,"is_route_hi":false,"is_normal":true,"is_lifted":true,"is_cancel":false},{"bkg_no":"CN06830017","shipper_no":"","shipper_name":"","pol":"","pod_country":"","pod":"","dly_country":"VN","dly_plc":"SGN","vsl":"","voy":"","lst_vsl":"FDR","lst_voy":"260605","lst_route":"KTS","booking_date":"2026년 6월 5일","booking_schedule":"2026년 6월 5일","cancel_date":"","week_start_date":"2026년 05월 31일","lead_time_bkg_sche":"Week of Sailing (WOS)","yyyymm_bkg_sche":"202606","lst_status":"Normal","fst_teu":3.0,"lst_teu":3.0,"norm_lst_teu":3.0,"cm1":1341.0,"norm_cm1":1341.0,"cm1_per_teu":447.0,"grade":"","route_profit":"고수익","shipper_profit_tag":"","is_w3":false,"is_hi":true,"is_route_hi":true,"is_normal":true,"is_lifted":true,"is_cancel":false},{"bkg_no":"CN06830111","shipper_no":"","shipper_name":"","pol":"","pod_country":"","pod":"","dly_country":"AE","dly_plc":"JEA","vsl":"","voy":"","lst_vsl":"JESN","lst_voy":"026B8W","lst_route":"AIMT","booking_date":"2026년 6월 27일","booking_schedule":"2026년 6월 27일","cancel_date":"","week_start_date":"2026년 06월 21일","lead_time_bkg_sche":"Week of Sailing (WOS)","yyyymm_bkg_sche":"202606","lst_status":"Waiting","fst_teu":2.0,"lst_teu":2.0,"norm_lst_teu":0.0,"cm1":6166.0,"norm_cm1":0.0,"cm1_per_teu":3083.0,"grade":"","route_profit":"","shipper_profit_tag":"","is_w3":false,"is_hi":false,"is_route_hi":false,"is_normal":false,"is_lifted":false,"is_cancel":false},{"bkg_no":"CN06830558","shipper_no":"","shipper_name":"","pol":"","pod_country":"","pod":"","dly_country":"TZ","dly_plc":"DAR","vsl":"","voy":"","lst_vsl":"JEMB","lst_voy":"02626W","lst_route":"EAX","booking_date":"2026년 6월 28일","booking_schedule":"2026년 6월 28일","cancel_date":"","week_start_date":"2026년 06월 28일","lead_time_bkg_sche":"Week of Sailing (WOS)","yyyymm_bkg_sche":"202606","lst_status":"Waiting","fst_teu":2.0,"lst_teu":2.0,"norm_lst_teu":0.0,"cm1":2436.0,"norm_cm1":0.0,"cm1_per_teu":1218.0,"grade":"","route_profit":"","shipper_profit_tag":"","is_w3":false,"is_hi":false,"is_route_hi":false,"is_normal":false,"is_lifted":false,"is_cancel":false},{"bkg_no":"CN06830560","shipper_no":"","shipper_name":"","pol":"","pod_country":"","pod":"","dly_country":"TZ","dly_plc":"DAR","vsl":"","voy":"","lst_vsl":"JEMB","lst_voy":"02626W","lst_route":"EAX","booking_date":"2026년 6월 28일","booking_schedule":"2026년 6월 28일","cancel_date":"","week_start_date":"2026년 06월 28일","lead_time_bkg_sche":"Week of Sailing (WOS)","yyyymm_bkg_sche":"202606","lst_status":"Waiting","fst_teu":2.0,"lst_teu":2.0,"norm_lst_teu":0.0,"cm1":2436.0,"norm_cm1":0.0,"cm1_per_teu":1218.0,"grade":"","route_profit":"","shipper_profit_tag":"","is_w3":false,"is_hi":false,"is_route_hi":false,"is_normal":false,"is_lifted":false,"is_cancel":false},{"bkg_no":"CN06830563","shipper_no":"","shipper_name":"","pol":"","pod_country":"","pod":"","dly_country":"TZ","dly_plc":"DAR","vsl":"","voy":"","lst_vsl":"JEMB","lst_voy":"02626W","lst_route":"EAX","booking_date":"2026년 6월 28일","booking_schedule":"2026년 6월 28일","cancel_date":"","week_start_date":"2026년 06월 28일","lead_time_bkg_sche":"Week of Sailing (WOS)","yyyymm_bkg_sche":"202606","lst_status":"Waiting","fst_teu":2.0,"lst_teu":2.0,"norm_lst_teu":0.0,"cm1":2436.0,"norm_cm1":0.0,"cm1_per_teu":1218.0,"grade":"","route_profit":"","shipper_profit_tag":"","is_w3":false,"is_hi":false,"is_route_hi":false,"is_normal":false,"is_lifted":false,"is_cancel":false},{"bkg_no":"CN06830567","shipper_no":"","shipper_name":"","pol":"","pod_country":"","pod":"","dly_country":"TZ","dly_plc":"DAR","vsl":"","voy":"","lst_vsl":"JEMB","lst_voy":"02626W","lst_route":"EAX","booking_date":"2026년 6월 28일","booking_schedule":"2026년 6월 28일","cancel_date":"","week_start_date":"2026년 06월 28일","lead_time_bkg_sche":"Week of Sailing (WOS)","yyyymm_bkg_sche":"202606","lst_status":"Waiting","fst_teu":2.0,"lst_teu":2.0,"norm_lst_teu":0.0,"cm1":2436.0,"norm_cm1":0.0,"cm1_per_teu":1218.0,"grade":"","route_profit":"","shipper_profit_tag":"","is_w3":false,"is_hi":false,"is_route_hi":false,"is_normal":false,"is_lifted":false,"is_cancel":false},{"bkg_no":"CN06830662","shipper_no":"","shipper_name":"","pol":"","pod_country":"","pod":"","dly_country":"AE","dly_plc":"JEA","vsl":"","voy":"","lst_vsl":"JESN","lst_voy":"026B8W","lst_route":"AIMT","booking_date":"2026년 6월 27일","booking_schedule":"2026년 6월 27일","cancel_date":"","week_start_date":"2026년 06월 21일","lead_time_bkg_sche":"Week of Sailing (WOS)","yyyymm_bkg_sche":"202606","lst_status":"Waiting","fst_teu":2.0,"lst_teu":2.0,"norm_lst_teu":0.0,"cm1":6166.0,"norm_cm1":0.0,"cm1_per_teu":3083.0,"grade":"","route_profit":"","shipper_profit_tag":"","is_w3":false,"is_hi":false,"is_route_hi":false,"is_normal":false,"is_lifted":false,"is_cancel":false},{"bkg_no":"CN06830663","shipper_no":"","shipper_name":"","pol":"","pod_country":"","pod":"","dly_country":"AE","dly_plc":"JEA","vsl":"","voy":"","lst_vsl":"JESN","lst_voy":"026B8W","lst_route":"AIMT","booking_date":"2026년 6월 27일","booking_schedule":"2026년 6월 27일","cancel_date":"","week_start_date":"2026년 06월 21일","lead_time_bkg_sche":"Week of Sailing (WOS)","yyyymm_bkg_sche":"202606","lst_status":"Waiting","fst_teu":2.0,"lst_teu":2.0,"norm_lst_teu":0.0,"cm1":6166.0,"norm_cm1":0.0,"cm1_per_teu":3083.0,"grade":"","route_profit":"","shipper_profit_tag":"","is_w3":false,"is_hi":false,"is_route_hi":false,"is_normal":false,"is_lifted":false,"is_cancel":false},{"bkg_no":"CN06830664","shipper_no":"","shipper_name":"","pol":"","pod_country":"","pod":"","dly_country":"AE","dly_plc":"JEA","vsl":"","voy":"","lst_vsl":"JESN","lst_voy":"026B8W","lst_route":"AIMT","booking_date":"2026년 6월 27일","booking_schedule":"2026년 6월 27일","cancel_date":"","week_start_date":"2026년 06월 21일","lead_time_bkg_sche":"Week of Sailing (WOS)","yyyymm_bkg_sche":"202606","lst_status":"Waiting","fst_teu":2.0,"lst_teu":2.0,"norm_lst_teu":0.0,"cm1":6166.0,"norm_cm1":0.0,"cm1_per_teu":3083.0,"grade":"","route_profit":"","shipper_profit_tag":"","is_w3":false,"is_hi":false,"is_route_hi":false,"is_normal":false,"is_lifted":false,"is_cancel":false},{"bkg_no":"CN06830666","shipper_no":"","shipper_name":"","pol":"","pod_country":"","pod":"","dly_country":"AE","dly_plc":"JEA","vsl":"","voy":"","lst_vsl":"JESN","lst_voy":"026B8W","lst_route":"AIMT","booking_date":"2026년 6월 27일","booking_schedule":"2026년 6월 27일","cancel_date":"","week_start_date":"2026년 06월 21일","lead_time_bkg_sche":"Week of Sailing (WOS)","yyyymm_bkg_sche":"202606","lst_status":"Waiting","fst_teu":2.0,"lst_teu":2.0,"norm_lst_teu":0.0,"cm1":6166.0,"norm_cm1":0.0,"cm1_per_teu":3083.0,"grade":"","route_profit":"","shipper_profit_tag":"","is_w3":false,"is_hi":false,"is_route_hi":false,"is_normal":false,"is_lifted":false,"is_cancel":false},{"bkg_no":"CN06830667","shipper_no":"","shipper_name":"","pol":"","pod_country":"","pod":"","dly_country":"AE","dly_plc":"JEA","vsl":"","voy":"","lst_vsl":"JESN","lst_voy":"026B8W","lst_route":"AIMT","booking_date":"2026년 6월 27일","booking_schedule":"2026년 6월 27일","cancel_date":"","week_start_date":"2026년 06월 21일","lead_time_bkg_sche":"Week of Sailing (WOS)","yyyymm_bkg_sche":"202606","lst_status":"Waiting","fst_teu":2.0,"lst_teu":2.0,"norm_lst_teu":0.0,"cm1":6166.0,"norm_cm1":0.0,"cm1_per_teu":3083.0,"grade":"","route_profit":"","shipper_profit_tag":"","is_w3":false,"is_hi":false,"is_route_hi":false,"is_normal":false,"is_lifted":false,"is_cancel":false},{"bkg_no":"CN06830669","shipper_no":"","shipper_name":"","pol":"","pod_country":"","pod":"","dly_country":"AE","dly_plc":"JEA","vsl":"","voy":"","lst_vsl":"JESN","lst_voy":"026B8W","lst_route":"AIMT","booking_date":"2026년 6월 27일","booking_schedule":"2026년 6월 27일","cancel_date":"","week_start_date":"2026년 06월 21일","lead_time_bkg_sche":"Week of Sailing (WOS)","yyyymm_bkg_sche":"202606","lst_status":"Waiting","fst_teu":2.0,"lst_teu":2.0,"norm_lst_teu":0.0,"cm1":6166.0,"norm_cm1":0.0,"cm1_per_teu":3083.0,"grade":"","route_profit":"","shipper_profit_tag":"","is_w3":false,"is_hi":false,"is_route_hi":false,"is_normal":false,"is_lifted":false,"is_cancel":false},{"bkg_no":"CN06830670","shipper_no":"","shipper_name":"","pol":"","pod_country":"","pod":"","dly_country":"AE","dly_plc":"JEA","vsl":"","voy":"","lst_vsl":"JESN","lst_voy":"026B8W","lst_route":"AIMT","booking_date":"2026년 6월 27일","booking_schedule":"2026년 6월 27일","cancel_date":"","week_start_date":"2026년 06월 21일","lead_time_bkg_sche":"Week of Sailing (WOS)","yyyymm_bkg_sche":"202606","lst_status":"Waiting","fst_teu":2.0,"lst_teu":2.0,"norm_lst_teu":0.0,"cm1":6166.0,"norm_cm1":0.0,"cm1_per_teu":3083.0,"grade":"","route_profit":"","shipper_profit_tag":"","is_w3":false,"is_hi":false,"is_route_hi":false,"is_normal":false,"is_lifted":false,"is_cancel":false},{"bkg_no":"CN06830672","shipper_no":"","shipper_name":"","pol":"","pod_country":"","pod":"","dly_country":"AE","dly_plc":"JEA","vsl":"","voy":"","lst_vsl":"JESN","lst_voy":"026B8W","lst_route":"AIMT","booking_date":"2026년 6월 27일","booking_schedule":"2026년 6월 27일","cancel_date":"","week_start_date":"2026년 06월 21일","lead_time_bkg_sche":"Week of Sailing (WOS)","yyyymm_bkg_sche":"202606","lst_status":"Waiting","fst_teu":2.0,"lst_teu":2.0,"norm_lst_teu":0.0,"cm1":6166.0,"norm_cm1":0.0,"cm1_per_teu":3083.0,"grade":"","route_profit":"","shipper_profit_tag":"","is_w3":false,"is_hi":false,"is_route_hi":false,"is_normal":false,"is_lifted":false,"is_cancel":false},{"bkg_no":"CN06830673","shipper_no":"","shipper_name":"","pol":"","pod_country":"","pod":"","dly_country":"AE","dly_plc":"JEA","vsl":"","voy":"","lst_vsl":"JESN","lst_voy":"026B8W","lst_route":"AIMT","booking_date":"2026년 6월 27일","booking_schedule":"2026년 6월 27일","cancel_date":"","week_start_date":"2026년 06월 21일","lead_time_bkg_sche":"Week of Sailing (WOS)","yyyymm_bkg_sche":"202606","lst_status":"Waiting","fst_teu":2.0,"lst_teu":2.0,"norm_lst_teu":0.0,"cm1":6166.0,"norm_cm1":0.0,"cm1_per_teu":3083.0,"grade":"","route_profit":"","shipper_profit_tag":"","is_w3":false,"is_hi":false,"is_route_hi":false,"is_normal":false,"is_lifted":false,"is_cancel":false},{"bkg_no":"CN06830674","shipper_no":"","shipper_name":"","pol":"","pod_country":"","pod":"","dly_country":"AE","dly_plc":"JEA","vsl":"","voy":"","lst_vsl":"JESN","lst_voy":"026B8W","lst_route":"AIMT","booking_date":"2026년 6월 27일","booking_schedule":"2026년 6월 27일","cancel_date":"","week_start_date":"2026년 06월 21일","lead_time_bkg_sche":"Week of Sailing (WOS)","yyyymm_bkg_sche":"202606","lst_status":"Waiting","fst_teu":2.0,"lst_teu":2.0,"norm_lst_teu":0.0,"cm1":6166.0,"norm_cm1":0.0,"cm1_per_teu":3083.0,"grade":"","route_profit":"","shipper_profit_tag":"","is_w3":false,"is_hi":false,"is_route_hi":false,"is_normal":false,"is_lifted":false,"is_cancel":false},{"bkg_no":"CN06830675","shipper_no":"","shipper_name":"","pol":"","pod_country":"","pod":"","dly_country":"AE","dly_plc":"JEA","vsl":"","voy":"","lst_vsl":"JESN","lst_voy":"026B8W","lst_route":"AIMT","booking_date":"2026년 6월 27일","booking_schedule":"2026년 6월 27일","cancel_date":"","week_start_date":"2026년 06월 21일","lead_time_bkg_sche":"Week of Sailing (WOS)","yyyymm_bkg_sche":"202606","lst_status":"Waiting","fst_teu":2.0,"lst_teu":2.0,"norm_lst_teu":0.0,"cm1":6166.0,"norm_cm1":0.0,"cm1_per_teu":3083.0,"grade":"","route_profit":"","shipper_profit_tag":"","is_w3":false,"is_hi":false,"is_route_hi":false,"is_normal":false,"is_lifted":false,"is_cancel":false},{"bkg_no":"CN06830676","shipper_no":"","shipper_name":"","pol":"","pod_country":"","pod":"","dly_country":"AE","dly_plc":"JEA","vsl":"","voy":"","lst_vsl":"JESN","lst_voy":"026B8W","lst_route":"AIMT","booking_date":"2026년 6월 27일","booking_schedule":"2026년 6월 27일","cancel_date":"","week_start_date":"2026년 06월 21일","lead_time_bkg_sche":"Week of Sailing (WOS)","yyyymm_bkg_sche":"202606","lst_status":"Waiting","fst_teu":1.0,"lst_teu":1.0,"norm_lst_teu":0.0,"cm1":0.0,"norm_cm1":0.0,"cm1_per_teu":0.0,"grade":"","route_profit":"","shipper_profit_tag":"","is_w3":false,"is_hi":false,"is_route_hi":false,"is_normal":false,"is_lifted":false,"is_cancel":false},{"bkg_no":"CN06830677","shipper_no":"","shipper_name":"","pol":"","pod_country":"","pod":"","dly_country":"AE","dly_plc":"JEA","vsl":"","voy":"","lst_vsl":"JESN","lst_voy":"026B8W","lst_route":"AIMT","booking_date":"2026년 6월 27일","booking_schedule":"2026년 6월 27일","cancel_date":"","week_start_date":"2026년 06월 21일","lead_time_bkg_sche":"Week of Sailing (WOS)","yyyymm_bkg_sche":"202606","lst_status":"Waiting","fst_teu":1.0,"lst_teu":1.0,"norm_lst_teu":0.0,"cm1":0.0,"norm_cm1":0.0,"cm1_per_teu":0.0,"grade":"","route_profit":"","shipper_profit_tag":"","is_w3":false,"is_hi":false,"is_route_hi":false,"is_normal":false,"is_lifted":false,"is_cancel":false},{"bkg_no":"CN06830776","shipper_no":"","shipper_name":"","pol":"","pod_country":"","pod":"","dly_country":"ID","dly_plc":"SUB","vsl":"","voy":"","lst_vsl":"JNGS","lst_voy":"0052S","lst_route":"KCS2","booking_date":"2026년 7월 1일","booking_schedule":"2026년 7월 1일","cancel_date":"","week_start_date":"2026년 06월 28일","lead_time_bkg_sche":"Week of Sailing (WOS)","yyyymm_bkg_sche":"202606","lst_status":"Waiting","fst_teu":1.0,"lst_teu":1.0,"norm_lst_teu":0.0,"cm1":584.0,"norm_cm1":0.0,"cm1_per_teu":584.0,"grade":"","route_profit":"","shipper_profit_tag":"","is_w3":false,"is_hi":false,"is_route_hi":false,"is_normal":false,"is_lifted":false,"is_cancel":false},{"bkg_no":"CN06830779","shipper_no":"","shipper_name":"","pol":"","pod_country":"","pod":"","dly_country":"ID","dly_plc":"SRG","vsl":"","voy":"","lst_vsl":"JNGS","lst_voy":"0052S","lst_route":"KCS2","booking_date":"2026년 7월 1일","booking_schedule":"2026년 7월 1일","cancel_date":"","week_start_date":"2026년 06월 28일","lead_time_bkg_sche":"Week of Sailing (WOS)","yyyymm_bkg_sche":"202606","lst_status":"Waiting","fst_teu":1.0,"lst_teu":1.0,"norm_lst_teu":0.0,"cm1":567.0,"norm_cm1":0.0,"cm1_per_teu":567.0,"grade":"","route_profit":"고수익","shipper_profit_tag":"","is_w3":false,"is_hi":true,"is_route_hi":true,"is_normal":false,"is_lifted":false,"is_cancel":false},{"bkg_no":"CN06830788","shipper_no":"","shipper_name":"","pol":"","pod_country":"","pod":"","dly_country":"OM","dly_plc":"SOH","vsl":"","voy":"","lst_vsl":"FDR","lst_voy":"260604","lst_route":"AIMT","booking_date":"2026년 6월 4일","booking_schedule":"2026년 6월 4일","cancel_date":"","week_start_date":"2026년 05월 31일","lead_time_bkg_sche":"Week of Sailing (WOS)","yyyymm_bkg_sche":"202606","lst_status":"Waiting","fst_teu":2.0,"lst_teu":2.0,"norm_lst_teu":0.0,"cm1":0.0,"norm_cm1":0.0,"cm1_per_teu":0.0,"grade":"","route_profit":"","shipper_profit_tag":"","is_w3":false,"is_hi":false,"is_route_hi":false,"is_normal":false,"is_lifted":false,"is_cancel":false},{"bkg_no":"CN06830789","shipper_no":"","shipper_name":"","pol":"","pod_country":"","pod":"","dly_country":"AE","dly_plc":"KLF","vsl":"","voy":"","lst_vsl":"FDR","lst_voy":"260604","lst_route":"AIMT","booking_date":"2026년 6월 4일","booking_schedule":"2026년 6월 4일","cancel_date":"","week_start_date":"2026년 05월 31일","lead_time_bkg_sche":"Week of Sailing (WOS)","yyyymm_bkg_sche":"202606","lst_status":"Waiting","fst_teu":2.0,"lst_teu":2.0,"norm_lst_teu":0.0,"cm1":0.0,"norm_cm1":0.0,"cm1_per_teu":0.0,"grade":"","route_profit":"","shipper_profit_tag":"","is_w3":false,"is_hi":false,"is_route_hi":false,"is_normal":false,"is_lifted":false,"is_cancel":false},{"bkg_no":"CN06830791","shipper_no":"","shipper_name":"","pol":"","pod_country":"","pod":"","dly_country":"AE","dly_plc":"KLF","vsl":"","voy":"","lst_vsl":"FDR","lst_voy":"260607","lst_route":"AIMT","booking_date":"2026년 6월 7일","booking_schedule":"2026년 6월 7일","cancel_date":"","week_start_date":"2026년 06월 07일","lead_time_bkg_sche":"Week of Sailing (WOS)","yyyymm_bkg_sche":"202606","lst_status":"Waiting","fst_teu":2.0,"lst_teu":2.0,"norm_lst_teu":0.0,"cm1":0.0,"norm_cm1":0.0,"cm1_per_teu":0.0,"grade":"","route_profit":"","shipper_profit_tag":"","is_w3":false,"is_hi":false,"is_route_hi":false,"is_normal":false,"is_lifted":false,"is_cancel":false},{"bkg_no":"CN06830792","shipper_no":"","shipper_name":"","pol":"","pod_country":"","pod":"","dly_country":"AE","dly_plc":"KLF","vsl":"","voy":"","lst_vsl":"FDR","lst_voy":"260607","lst_route":"AIMT","booking_date":"2026년 6월 7일","booking_schedule":"2026년 6월 7일","cancel_date":"","week_start_date":"2026년 06월 07일","lead_time_bkg_sche":"Week of Sailing (WOS)","yyyymm_bkg_sche":"202606","lst_status":"Waiting","fst_teu":2.0,"lst_teu":2.0,"norm_lst_teu":0.0,"cm1":0.0,"norm_cm1":0.0,"cm1_per_teu":0.0,"grade":"","route_profit":"","shipper_profit_tag":"","is_w3":false,"is_hi":false,"is_route_hi":false,"is_normal":false,"is_lifted":false,"is_cancel":false}]}